{
  "阿姨": "พี่สาว",
  "啊": "(คำอุทาน)",
  "矮": "ตัวเล็ก",
  "矮小": "ตัวเล็กและเตี้ย",
  "爱国": "รักชาติ",
  "爱护": "รักษา",
  "安": "นามสกุลอัน",
  "安置": "จัดที่ให้",
  "按时": "ตรงเวลา",
  "暗": "ไม่ชัดเจน",
  "暗示": "ให้สัญญาณ",
  "巴士": "รถเมล์",
  "百货": "สินค้าทั่วไป",
  "摆": "วาง",
  "摆动": "แกว่ง",
  "摆脱": "หลุดพ้น",
  "败": "พ่ายแพ้",
  "办事": "จัดการ",
  "包裹": "ห่อ",
  "包含": "รวมถึง",
  "包括": "รวมถึง",
  "薄": "ไม่อบอุ่น",
  "宝": "ของมีค่า",
  "宝宝": "ลูกคู่",
  "宝贝": "ลูกน้อย",
  "宝贵": "ของมีค่า",
  "宝石": "มีค่า",
  "保密": "อัญมณี",
  "保守": "รักษาความลับ",
  "抱": "รักษา",
  "背景": "บริบท",
  "倍": "เท่ากับ",
  "被迫": "ถูกบังคับ",
  "本科": "หลักสูตรปริญญาตรี",
  "笨": "โง่",
  "比分": "คะแนน",
  "毕业": "สำเร็จการศึกษา",
  "毕业生": "ผู้สำเร็จการศึกษา",
  "避": "หลีกเลี่ยง",
  "避免": "หลีกเลี่ยง",
  "编": "จัดกลุ่ม",
  "辩论": "อภิปราย",
  "标志": "เครื่องหมาย",
  "表情": "สีหน้า",
  "表扬": "ชื่นชม",
  "别": "อย่า",
  "冰": "น้ำแข็ง",
  "冰箱": "ตู้เย็น",
  "冰雪": "น้ำแข็งและหิมะ",
  "兵": "ทหาร",
  "并": "อยู่ข้างเคียง",
  "不要紧": "ไม่สำคัญ",
  "不在乎": "ไม่สนใจ",
  "不管": "ไม่ว่า",
  "不然": "ถ้าไม่เช่นนั้น",
  "布置": "จัดวาง",
  "步行": "เดิน",
  "擦": "เช็ด",
  "才": "เพียงแต่",
  "材料": "วัสดุ",
  "财产": "สิ่งของ",
  "财富": "ความมั่งคั่ง",
  "采访": "สัมภาษณ์",
  "参考": "consult",
  "参与": "participate in",
  "操场": "schoolyard",
  "操作": "operate",
  "测": "measure out",
  "测量": "survey",
  "测试": "test",
  "曾": "once",
  "茶叶": "tea",
  "产品": "baby",
  "长途": "long-distance",
  "常识": "nous",
  "唱片": "pressing",
  "抄": "to make a copy",
  "抄写": "to copy",
  "潮": "tide",
  "潮流": "stream",
  "潮湿": "damp",
  "彻底": "thorough",
  "沉": "see 黑沉沉[hei1 chen1 chen1]",
  "沉默": "taciturn",
  "沉重": "heavy",
  "称赞": "to praise",
  "成人": "grownup",
  "诚实": "honest",
  "诚信": "genuine",
  "承担": "bear",
  "承认": "รับรู้, ยอมรับ",
  "承受": "รับผิดชอบ, รับน้ำหนัก",
  "程序": "ลำดับ, ขั้นตอน",
  "吃惊": "ตกใจ, ประหลาดใจ",
  "迟到": "สาย, ไปช้า",
  "尺": "เมตร, หน่วย",
  "尺寸": "ขนาด, ความยาว",
  "尺子": "ไม้บรรทัด, เครื่องวัด",
  "冲": "พุ่ง, กระชาก",
  "充电": "ชาร์จ, ชาร์จไฟ",
  "充电器": "เครื่องชาร์จ, ตัวชาร์จ",
  "充分": "เต็ม, มาก",
  "虫子": "แมลง, สัตว์",
  "抽": "ตี, ฟัน",
  "抽奖": "จับฉลาก, จับรางวัล",
  "抽烟": "สูบ, สูบบุหรี่",
  "出口": "ส่งออก, นำออก",
  "出色": "โดดเด่น, ดี",
  "出售": "ขาย, ขายของ",
  "出席": "เข้าร่วม, ไป",
  "处于": "อยู่, อยู่ใน",
  "处": "หน่วย, หน่วยทั่วไป",
  "穿上": "สวม, ใส่",
  "传统": "ประเพณี, วัฒนธรรม",
  "窗户": "หน้าต่าง",
  "窗台": "ขอบหน้าต่าง, ขอบ",
  "窗子": "หน้าต่าง",
  "春季": "ฤดูใบไม้ผลิ, ฤดูใบไม้ผล",
  "纯": "บริสุทธิ์",
  "纯净水": "น้ำบริสุทธิ์, น้ำสะอาด",
  "词汇": "คำศัพท์, คำศัพท์ในสมอง",
  "此": "นี่",
  "此外": "นอกจากนี้",
  "次": "ลำดับ",
  "刺": "แทง",
  "刺激": "กระตุ้น",
  "从此": "ตั้งแต่นี้ไป",
  "粗": "กว้าง",
  "粗心": "ไม่ใส่ใจ",
  "促进": "เร่ง",
  "促使": "กระตุ้น",
  "促销": "การขายส่ง",
  "措施": "มาตรการ",
  "打": "กระทำ",
  "答案": "คำตอบ",
  "打败": "พ่ายแพ้",
  "打雷": "ฟ้าร้อง",
  "打扫": "ทำความสะอาด",
  "打折": "ลดราคา",
  "打针": "ฉีดยา",
  "大巴": "รถบัสใหญ่",
  "大多": "ส่วนใหญ่",
  "大方": "ผู้เชี่ยวชาญ",
  "大哥": "พี่ชาย",
  "大规模": "ขนาดใหญ่",
  "大会": "ประชุม",
  "大姐": "พี่สาว",
  "大楼": "อาคาร",
  "大陆": "แผ่นดินใหญ่",
  "大妈": "แม่หม้าย",
  "大型": "ขนาดใหญ่, ขนาด",
  "大爷": "ผู้ชายสูงอายุ, ผู้ชาย",
  "大众": "ประชาชน, กลุ่มคน",
  "代替": "แทนที่, แทน",
  "待遇": "การปฏิบัติ, ค่าจ้าง",
  "袋": "ถุง, กระเป๋า",
  "戴": "สวม, ใส่",
  "担保": "รับประกัน, รับรอง",
  "担任": "รับตำแหน่ง, ดำรงตำแหน่ง",
  "担心": "กังวล, ห่วง",
  "单": "เดี่ยว, แยก",
  "单纯": "เรียบง่าย, ไม่ซับซ้อน",
  "单调": "น่าเบื่อ, ซ้ำซาก",
  "单独": "แยกตัว, อย่างเดียว",
  "淡": "ไม่มีรสชาติ, ไม่มีรส",
  "导游": "ไกด์ทัวร์, ผู้นำเที่ยว",
  "导致": "ก่อให้เกิด, ทำให้เกิด",
  "倒闭": "ล้มละลาย, ล้ม",
  "倒车": "เปลี่ยนรถ, ขึ้นรถใหม่",
  "得意": "ภูมิใจ, ภาคภูมิใจ",
  "得": "(แสดงผลลัพธ์)",
  "灯光": "แสงไฟ, แสง",
  "登": "ปีน, ปีนขึ้น",
  "登记": "ลงทะเบียน, จดบันทึก",
  "登录": "ลงทะเบียน, ลงชื่อ",
  "登山": "ปีนเขา, ขึ้นเขา",
  "的确": "แน่นอน, จริง",
  "敌人": "ศัตรู",
  "底": "ด้านล่าง, ด้าน",
  "地方": "ประเทศ, พื้นที่",
  "地面": "พื้นผิว, พื้นดิน",
  "地位": "สถานะ, ตำแหน่ง",
  "地下": "ใต้ดิน, ชั้นใต้ดิน",
  "地址": "ที่ตั้ง, ที่อยู่",
  "典型": "ตัวอย่าง, ลักษณะ",
  "点名": "การเรียกชื่อ, การเรียกชื่อในชั้นเรียน",
  "电灯": "หลอดไฟ, หลอดไฟฟ้า",
  "电动车": "ยานพาหนะไฟฟ้า, รถจักรยานไฟฟ้า",
  "电梯": "ลิฟต์, ลิฟต์ในอาคาร",
  "电源": "แหล่งพลังงานไฟฟ้า, แหล่งไฟฟ้า",
  "顶": "ยอด, หัว",
  "定": "ตัดสินใจ, กำหนด",
  "冬季": "ฤดูหนาว",
  "动画片": "ภาพยนตร์แอนิเมชัน, หนังการ์ตูน",
  "动摇": "สั่น, เคลื่อนไหว",
  "豆腐": "เต้าหู้, อาหารเต้าหู้",
  "独立": "อิสระ, แยกตัว",
  "独特": "พิเศษ, ไม่เหมือนใคร",
  "独自": "คนเดียว, ไม่มีใครช่วย",
  "堵": "อุด, ปิด",
  "堵车": "รถติด, จราจรติด",
  "肚子": "ท้อง, กระเพาะ",
  "度过": "ผ่านไป, ใช้เวลา",
  "锻炼": "ฝึกฝน, ออกกำลังกาย",
  "对比": "เปรียบเทียบ, ความสัมพันธ์",
  "对付": "ต่อสู้, จัดการ",
  "对于": "เกี่ยวกับ, สำหรับ",
  "多次": "หลายครั้ง",
  "多年": "นานหลายปี",
  "多样": "หลากหลาย, หลายแบบ",
  "多种": "หลายชนิด, หลากหลาย",
  "恶心": "คลื่นไส้, คลื่นเหว",
  "儿童": "เด็ก, เด็กเล็ก",
  "而": "(คำเชื่อม) แต่",
  "而是": "(คำเชื่อม) ไม่ใช่",
  "耳机": "หูฟัง, หูฟังเสียง",
  "二手": "ของมือสอง, ของที่ถูกถ่ายโอน",
  "发挥": "ใช้ความสามารถ, แสดงออก",
  "发票": "ใบเสร็จ, ใบกำกับ",
  "发烧": "ไข้, ตัวร้อน",
  "法": "กฎหมาย, ระเบียบ",
  "法官": "ผู้พิพากษา, ผู้ตัดสิน",
  "法律": "รัฐธรรมนูญ, กฎหมาย",
  "法院": "ศาล, ศาลยุติธรรม",
  "翻": "พลิก, กลับ",
  "翻译": "แปล, แปลภาษา",
  "烦": "รู้สึกหงุดหงิด, รู้สึกไม่พอใจ",
  "反": "กลับ, ตรงข้าม",
  "反而": "(คำเชื่อม) แต่",
  "反映": "สะท้อน, แสดงออก",
  "方": "เพิ่ง, ตอนนี้",
  "方案": "แผน, วิธี",
  "方针": "นโยบาย, หลักการ",
  "放松": "ผ่อนคลาย, คลายความตึงเครียด",
  "非": "ไม่, ไม่ใช่",
  "肥": "อ้วน, หนัก",
  "分布": "กระจาย, แพร่หลาย",
  "分散": "กระจาย, แยกออก",
  "分手": "เลิก, หยุด",
  "分为": "แบ่ง, แบ่งออก",
  "…分之…": "...ของ...",
  "纷纷": "อย่างหนาแน่น",
  "奋斗": "ต่อสู้",
  "风格": "แผน",
  "风景": "ทัศนียภาพ",
  "风俗": "ประเพณี",
  "封闭": "ปิดกั้น",
  "否则": "ถ้าไม่เช่นนั้น",
  "夫妇": "คู่สมรส",
  "夫妻": "คู่รัก",
  "夫人": "ภรรยา",
  "符号": "สัญลักษณ์",
  "符合": "ตรงกัน",
  "付出": "จ่าย",
  "负担": "ภาระ",
  "附近": "ใกล้เคียง",
  "复制": "สำเนา",
  "改善": "ปรับปรุง",
  "改正": "แก้ไข",
  "盖": "ปิด",
  "概括": "สรุป",
  "感兴趣": "สนใจ",
  "高潮": "คลื่นสูง",
  "高价": "ราคาสูง",
  "高尚": "สูงส่ง, (คำคุณศัพท์)",
  "高铁": "รถไฟความเร็วสูง",
  "格外": "พิเศษ, (คำคุณศัพท์)",
  "隔": "แยก",
  "隔开": "แยกออก",
  "个别": "เฉพาะ, (คำคุณศัพท์)",
  "个体": "หน่วย",
  "各个": "ทุก",
  "根": "ราก",
  "根据": "ตาม",
  "工程": "กระบวนการ",
  "公元": "ปีคริสต์ศักราช",
  "供应": "การจัดหา",
  "共": "ทั้งหมด",
  "构成": "ประกอบด้วย",
  "构造": "โครงสร้าง",
  "购买": "ซื้อ",
  "购物": "การช้อปปิ้ง",
  "骨头": "กระดูก",
  "固定": "ตั้งค่า",
  "瓜": "แตงโม",
  "怪": "รู้สึกแปลก",
  "关": "ปิด",
  "关闭": "ปิด",
  "关于": "เกี่ยวกับ",
  "官": "ข้าราชการ",
  "官方": "ทางการ",
  "光临": "มาเยี่ยม",
  "光盘": "ดีวีดี",
  "逛": "เดินเล่น",
  "归": "คืน",
  "规律": "กฎ",
  "规模": "ขนาด",
  "规则": "กฎ",
  "果实": "ผลผลิต",
  "过分": "เกินไป",
  "海水": "น้ำทะเล",
  "海鲜": "อาหารทะเล",
  "含": "เก็บไว้ในปาก",
  "含量": "ปริมาณ",
  "含义": "ความหมาย",
  "含有": "มี",
  "寒假": "ช่วงวันหยุดฤดูหนาว",
  "寒冷": "เย็น",
  "行业": "อาชีพ",
  "航班": "เที่ยวบิน",
  "航空": "การบิน",
  "毫米": "มิลลิเมตร",
  "毫升": "มิลลิลิตร",
  "好友": "เพื่อนสนิท",
  "号码": "หมายเลข",
  "好": "ดี",
  "合同": "สัญญา",
  "黑暗": "ความมืด",
  "红包": "เงินในซองแดง",
  "后头": "ด้านหลัง",
  "厚": "หนา",
  "呼吸": "หายใจ",
  "忽视": "ละเลย",
  "户": "(หน่วยนับทั่วไป)",
  "护士": "พยาบาล",
  "花": "ดอกไม้",
  "划": "ตัด",
  "怀念": "ระลึกถึง",
  "怀疑": "สงสัย",
  "缓解": "บรรเทา",
  "黄瓜": "แตงกวา, ผักแตงกวา",
  "黄金": "ทองคำ, โลหะมีค่า",
  "回复": "ตอบกลับ, ตอบ",
  "汇": "โอนเงิน, จ่ายเงิน",
  "汇报": "รายงาน, สรุป",
  "汇率": "อัตราแลกเปลี่ยน, อัตราแลกเงิน",
  "婚礼": "พิธีแต่งงาน, งานแต่งงาน",
  "火": "ไฟ, ความร้อนภายใน",
  "伙": "เพื่อน, คู่",
  "伙伴": "คู่, เพื่อน",
  "或许": "อาจ, อาจจะ",
  "货": "สินค้า, ของ",
  "获": "เก็บเกี่ยว, ผลผลิต",
  "获得": "พบ, ได้มา",
  "获奖": "ได้รับรางวัล, ได้รางวัล",
  "获取": "ได้รับ, ได้มา",
  "几乎": "เกือบ, แทบจะ",
  "机构": "โครงสร้าง, ระบบ",
  "机遇": "โอกาส, ช่วงเวลา",
  "积累": "สะสม",
  "激动": "ตื่นเต้น, กระวนกระวาย",
  "激烈": "รุนแรง, ดุเดือด",
  "及格": "ผ่าน, ผ่านการสอบ",
  "极": "สูงสุด, ขั้นสูงสุด",
  "极其": "อย่างมาก, อย่างสิ้นเชิง",
  "即将": "กำลังจะ, ใกล้จะ",
  "急忙": "รีบ, รีบเร่ง",
  "集合": "รวมตัว, รวมกลุ่ม",
  "记载": "บันทึก, จดบันทึก",
  "纪律": "วินัย, ระเบียบวินัย",
  "技巧": "ทักษะ, ความสามารถ",
  "系": "เป็น, อยู่",
  "季": "นามสกุลจี้, ชื่อจี้",
  "季度": "ไตรมาส, ช่วงเวลา",
  "季节": "ฤดูกาล, ฤดู",
  "既": "แล้ว, แล้ว...แล้ว",
  "既然": "เนื่องจาก, เพราะ",
  "寄": "ติด, แนบ",
  "加班": "ทำงานล่วงเวลา, ทำงานเกินเวลา",
  "加入": "เข้าร่วม, รวมตัว",
  "加油站": "จุดเติมน้ำมัน, สถานีน้ำมัน",
  "家务": "งานบ้าน, ภาระบ้าน",
  "假如": "ถ้า, หาก",
  "坚固": "แข็งแรง, แน่น",
  "检测": "ตรวจ, วัด",
  "减": "ลดลง, ถูกตี",
  "减肥": "ลดน้ำหนัก, ผอมลง",
  "减少": "ลดลง, ลดน้อยลง",
  "简历": "ประวัติส่วนตัว, บันทึกชีวิต",
  "健身": "ออกกำลังกาย, ออกแรง",
  "渐渐": "ค่อยๆ",
  "江": "แม่น้ำ, น้ำ",
  "讲究": "ใส่ใจ, สนใจ",
  "讲座": "การบรรยาย, การพูด",
  "奖": "รางวัล, ของรางวัล",
  "奖金": "เงินรางวัล, โบนัส",
  "奖学金": "ทุนการศึกษา, ทุน",
  "降": "ลดลง, ตก",
  "降低": "ลดลง",
  "降价": "ลดราคา",
  "降落": "ลดลง, ลง",
  "降温": "ลดอุณหภูมิ, ลดความร้อน",
  "交换": "แลกเปลี่ยน, แลก",
  "交际": "การสื่อสาร, การติดต่อ",
  "教授": "ศาสตราจารย์, อาจารย์",
  "教训": "บทเรียน, บทสอน",
  "阶段": "ขั้นตอน, ช่วงเวลา",
  "街道": "ถนน, ย่าน",
  "节省": "ประหยัด, ลดค่าใช้จ่าย",
  "结": "ผูก, ปม",
  "结构": "โครงสร้าง, ระบบ",
  "结论": "ข้อสรุป, ผลสรุป",
  "姐妹": "พี่น้อง, ลูกสาว",
  "解释": "อธิบาย, ให้ความหมาย",
  "尽快": "เร็วที่สุด, ให้เร็ว",
  "紧密": "แน่น, ใกล้ชิด",
  "尽力": "พยายาม, ทุ่มเท",
  "进口": "นำเข้า",
  "近代": "ยุคใหม่, ยุคปัจจุบัน",
  "禁止": "ห้าม, ห้ามทำ",
  "经典": "นิรันดร, คลาสสิก",
  "精力": "พลังงาน, ความแข็งแรง",
  "竟然": "อย่างไม่น่าเชื่อ, อย่างน่าประหลาดใจ",
  "镜头": "กล้อง, กล้องถ่ายภาพ",
  "镜子": "กระจก, กระจกเงา",
  "究竟": "จริงๆ, แน่นอน",
  "酒吧": "บาร์, สถานที่ดื่ม",
  "居民": "ผู้อยู่อาศัย, ประชาชน",
  "居住": "อยู่อาศัย, อาศัย",
  "局": "หน่วยงาน, สำนักงาน",
  "巨大": "ขนาดใหญ่, ขนาดมหึมา",
  "具备": "มี, ได้รับ",
  "距离": "ระยะห่าง, ระยะ",
  "聚": "รวมตัว, รวมกลุ่ม",
  "聚会": "การรวมตัว, การรวมกลุ่ม",
  "卷": "เล่ม, ชุด",
  "角色": "บทบาท, ตัวละคร",
  "开花": "บาน, ผลักดัน",
  "开水": "น้ำเดือด, น้ำต้ม",
  "看不起": "ไม่เห็นคุณค่า, ดูถูก",
  "看来": "ดูเหมือน, ดูเหมือนจะ",
  "看望": "เยี่ยมเยียน, ไปเยี่ยม",
  "考察": "ตรวจสอบ, สำรวจ",
  "考虑": "พิจารณา, คิด",
  "棵": "ต้น, หัว",
  "可见": "ดังนั้น, จึง",
  "空间": "พื้นที่, ช่องว่าง",
  "空": "ว่าง, ไม่มี",
  "口袋": "กระเป๋า, ถุง",
  "口语": "ภาษาพูด, ภาษาที่ใช้พูด",
  "苦": "ทุกข์, ลำบาก",
  "会计": "บัญชี, ผู้จัดการบัญชี",
  "快递": "การส่งของเร่งด่วน, บริการส่งของเร่งด่วน",
  "宽": "กว้าง, ขยาย",
  "宽广": "กว้าง, ใหญ่",
  "矿泉水": "น้ำแร่, น้ำพุ",
  "扩大": "ขยาย, ขยายขนาด",
  "扩展": "ขยาย, ขยายตัว",
  "括号": "วงเล็บ, วงเล็บปีก",
  "垃圾": "ขยะ, ของเหลือทิ้ง",
  "拉开": "เปิดออก, ดึงออก",
  "辣": "เผ็ด, ร้อนจัด",
  "来不及": "ไม่ทัน, ไม่ทันเวลา",
  "来得及": "ยังทัน, ยังมีเวลา",
  "来源": "แหล่งที่มา, ที่มา",
  "老公": "ชายชรา, สามี",
  "老家": "บ้านเกิด, บ้านเดิม",
  "老婆": "หญิงชรา, ภรรยา",
  "老实": "ซื่อสัตย์, จริงใจ",
  "乐趣": "ความสนุก, ความเพลิดเพลิน",
  "泪": "น้ำตา, น้ำตาล",
  "泪水": "น้ำตาล, น้ำตา",
  "类型": "ประเภท, ชนิด",
  "冷静": "สงบ, ใจเย็น",
  "厘米": "เซนติเมตร",
  "离不开": "ไม่สามารถแยกจากได้, ติดอยู่",
  "力气": "พลัง, แรง",
  "历史": "ประวัติศาสตร์, อดีต",
  "立即": "ทันที, ทันทีทันใด",
  "利息": "ดอกเบี้ย",
  "利益": "ผลประโยชน์, ประโยชน์",
  "俩": "สอง, สองคน",
  "良好": "ดี, ดีมาก",
  "量": "น้ำหนัก, วัด",
  "粮食": "อาหาร, ข้าวของ",
  "两边": "สองข้าง, ทั้งสองฝั่ง",
  "疗养": "พักฟื้น, รักษา",
  "了不起": "น่าทึ่ง, น่าประทับใจ",
  "了解": "เข้าใจ, รู้เรื่อง",
  "列": "จัดเรียง, จัดลำดับ",
  "列车": "รถไฟ, จัดอยู่ใน",
  "列入": "ถูกจัดไว้, ถูกใส่ไว้",
  "列为": "ถูกจัดเป็น, ถูกจัดให้เป็น",
  "临时": "ใกล้ถึงเวลา, ใกล้จะ",
  "零食": "ของว่างระหว่างมื้อ, ของกินเล่น",
  "流传": "แพร่หลาย, แพร่กระจาย",
  "楼梯": "บันได, ทางเดิน",
  "陆地": "พื้นดิน, แผ่นดิน",
  "陆续": "ต่อเนื่อง, ไม่หยุด",
  "录取": "รับเข้าเรียน, รับเข้า",
  "律师": "นักกฎหมาย, ทนาย",
  "轮": "(หน่วยนับเหตุการณ์)",
  "轮船": "เรือไอน้ำ, เรือกลไฟ",
  "轮椅": "รถเข็น, รถเข็นผู้พิการ",
  "轮子": "ล้อ, ล้อรถ",
  "论文": "บทความวิชาการ, บทความ",
  "落": "ตกลง, ตก",
  "毛巾": "ผ้าเช็ดหน้า, ผ้าเช็ดตัว",
  "毛衣": "เสื้อไหม, เสื้อผ้าไหม",
  "帽子": "หมวก, หมวกปีกกว้าง",
  "没错": "ถูกต้อง, ไม่ผิด",
  "没法儿": "ไม่สามารถ, ไม่ได้",
  "没想到": "ไม่คาดคิด, ไม่ทันคาด",
  "美金": "เงินดอลลาร์, เงินสหรัฐ",
  "美女": "ผู้หญิงสวย, สาวสวย",
  "梦": "ความฝัน, ฝัน",
  "梦见": "ฝันถึง, ฝันว่า",
  "梦想": "ความฝัน, ความปรารถนา",
  "秘密": "ความลับ, ความลับส่วนตัว",
  "秘书": "ลูกจ้าง, เลขานุการ",
  "密": "หนา, แน่น",
  "密码": "รหัส, รหัสผ่าน",
  "密切": "ใกล้ชิด, เข้าใจกัน",
  "免费": "ฟรี, ไม่เสียค่าใช้จ่าย",
  "面临": "เผชิญ, ต้องพบกับ",
  "面试": "สัมภาษณ์",
  "描述": "อธิบาย, บรรยาย",
  "描写": "อธิบาย, บรรยาย",
  "名牌儿": "แบรนด์ชื่อดัง",
  "名片": "บัตรเยี่ยมเยียน",
  "名人": "บุคคลที่มีชื่อเสียง",
  "摸": "สัมผัส, คลำ",
  "模特儿": "แบบจำลอง, ต้นแบบ",
  "模型": "รูปแบบ, ตัวอย่าง",
  "末": "ปลาย, ปลายสุด",
  "默默": "เงียบ, สงบ",
  "哪怕": "แม้, แม้ว่า",
  "哪": "ที่ไหน, อัน/คน/สิ่งไหน",
  "男女": "ชายและหญิง, ผู้ชายและผู้หญิง",
  "男士": "ผู้ชาย, ชาย",
  "难免": "หลีกเลี่ยงไม่ได้, ไม่อาจหลีกเลี่ยงได้",
  "脑袋": "ศีรษะ, หัว",
  "闹": "ร้องเสียงดัง, ทำให้เกิดความวุ่นวาย",
  "闹钟": "นาฬิกาปลุก",
  "内部": "ภายใน",
  "内科": "เวชศาสตร์ภายใน, แพทย์แผนภายใน",
  "能干": "มีความสามารถ, ความสามารถ",
  "宁静": "สงบ, สงบเงียบ",
  "浓": "หนา, หนาแน่น",
  "女士": "ผู้หญิง, หญิง",
  "暖气": "ระบบทำความร้อน, ระบบปรับอากาศ",
  "拍照": "ถ่ายภาพ",
  "排列": "จัดเรียง",
  "牌": "โดมิโน",
  "盘": "เหตุการณ์",
  "盘子": "จาน",
  "胖子": "คนอ้วน",
  "培训": "ปลูกฝัง",
  "培训班": "ชั้นเรียนฝึกอบรม",
  "培养": "ส่งเสริม",
  "培育": "ปลูกฝัง",
  "批": "หน่วย, จำนวน",
  "片面": "ข้างเดียว",
  "品质": "คุณภาพ",
  "平方": "ตาราง",
  "平静": "สงบ",
  "平均": "เฉลี่ย",
  "平稳": "เรียบ",
  "迫切": "เร่งด่วน",
  "破产": "ล้มละลาย",
  "妻子": "ภรรยา",
  "期待": "คาดหวัง",
  "期间": "ระยะเวลา",
  "期末": "สิ้นภาค",
  "期限": "กำหนดเวลา",
  "期中": "ระหว่างภาค",
  "其余": "อื่นๆ",
  "企业": "องค์กร",
  "气球": "ลูกโป่ง",
  "汽水": "น้ำอัดลม",
  "汽油": "น้ำมัน, ชิ้นส่วน",
  "器官": "อวัยวะ, ชิ้นส่วน",
  "前头": "หน้า, ด้านหน้า",
  "前途": "ทิศทาง, อนาคต",
  "浅": "ตื้น, ไม่ลึก",
  "巧克力": "ช็อกโกแลต",
  "切": "ตัด, หั่น",
  "亲爱": "รัก, ใกล้ชิด",
  "亲密": "ใกล้ชิด, สนิท",
  "青春": "ฤดูใบไม้ผลิ",
  "轻松": "เบา, ไม่หนัก",
  "轻易": "เบา, ไม่หนัก",
  "清醒": "ตื่น, ตื่นขึ้น",
  "情景": "ฉาก, สถานการณ์",
  "穷": "หมด, หมดสิ้น",
  "穷人": "คนยากจน, ผู้ยากจน",
  "秋季": "ฤดูใบไม้ร่วง",
  "趋势": "แนวโน้ม, ทิศทาง",
  "圈": "วง, วงกลม",
  "权利": "สิทธิ, อำนาจ",
  "却": "แม้ว่า, แต่",
  "确认": "ยืนยัน",
  "然而": "แต่, อย่างไรก็ตาม",
  "燃料": "เชื้อเพลิง, วัสดุเผาไหม้",
  "燃烧": "เผาไหม้, ไหม้",
  "热闹": "คึกคัก, สนุก",
  "热心": "กระตือรือร้น",
  "人家": "ฉัน, ตัวฉัน",
  "日记": "บันทึกประจำวัน, บันทึก",
  "日历": "ปฏิทิน",
  "如今": "ในปัจจุบัน, ปัจจุบัน",
  "弱": "อ่อนแอ, ไม่แข็งแรง",
  "伞": "ร่ม, ช่องว่าง",
  "散": "กระจาย, แยก",
  "扫": "กวาด, ถู",
  "色": "สี, โทนสี",
  "色彩": "สีสัน, โทนสี",
  "耕": "ไถ, ไถพรวน",
  "晒": "ตาก, แห้ง",
  "闪": "บวม, ข้อเท้าบวม",
  "闪电": "ฟ้าผ่า, ฟ้าร้อง",
  "善良": "ดี, ใจดี",
  "善于": "เก่ง, ชำนาญ",
  "伤害": "ทำร้าย, ทำลาย",
  "商务": "การค้า, การธุรกิจ",
  "赏": "ชื่นชม, ชม",
  "上个月": "เดือนที่แล้ว, เดือนก่อน",
  "上楼": "ขึ้นบันได, ขึ้นชั้น",
  "上门": "มาเยี่ยม, มาเยือน",
  "烧": "เผา, อบ",
  "设施": "อุปกรณ์, ระบบ",
  "设置": "ตั้ง, จัด",
  "申请": "ยื่นคำขอ, ขอ",
  "身材": "รูปร่าง",
  "身份": "สถานะ, สถานการณ์",
  "身高": "ความสูง",
  "深厚": "ลึก",
  "神话": "นิทาน, เรื่องเล่า",
  "神秘": "ลึกลับ",
  "甚至": "แม้แต่, แม้ถึง",
  "失败": "ความพ่ายแพ้, ความผิดหวัง",
  "失望": "รู้สึกผิดหวัง, ผิดหวัง",
  "失业": "สูญเสียงาน, ว่างงาน",
  "诗": "บทกวี, รูปแบบบทกวี",
  "诗人": "นักกวี, ผู้ให้แรงบันดาลใจ",
  "湿": "ชื้น, ทำให้ชื้น",
  "实施": "ดำเนินการ, นำไปปฏิบัติ",
  "实用": "ใช้ได้จริง, ประโยชน์",
  "食堂": "ห้องอาหาร, โรงอาหาร",
  "使劲": "ใช้แรงทั้งหมด, ใช้แรง",
  "士兵": "ทหาร, ทหารรับใช้",
  "市区": "พื้นที่เมือง",
  "似的": "เหมือน, ดูเหมือน",
  "事物": "สิ่งของ, สิ่งต่าง ๆ",
  "事先": "ล่วงหน้า, ก่อน",
  "试卷": "แบบทดสอบ, ข้อสอบ",
  "是否": "หรือไม่",
  "收回": "คืน, รับคืน",
  "收获": "เก็บเกี่ยว, ผลผลิต",
  "收益": "รายได้, ผลตอบแทน",
  "手工": "งานมือ, งานฝีมือ",
  "手里": "ในมือ, อยู่ในมือ",
  "手术": "การผ่าตัด, ผ่าตัด",
  "手套": "ถุงมือ",
  "守": "ปกป้อง, ดูแล",
  "首": "หัว, หัวหน้า",
  "受不了": "ทนไม่ไหว, ทนไม่ได้",
  "售货员": "พนักงานขาย",
  "叔叔": "พี่ชายของพ่อ, พี่ชายพ่อ",
  "舒适": "สบาย, สะดวก",
  "熟练": "ทักษะ, ชำนาญ",
  "暑假": "วันหยุดฤดูร้อน, ช่วงวันหยุดฤดูร้อน",
  "树林": "ป่า, ป่าไม้",
  "树叶": "ใบไม้",
  "数据": "ข้อมูล",
  "数码": "ตัวเลข, จำนวน",
  "刷": "แปรง, ขัด",
  "刷牙": "แปรงฟัน",
  "刷子": "แปรง",
  "帅": "นามสกุลชุย",
  "帅哥": "หนุ่มหล่อ",
  "率先": "นำหน้า, นำทาง",
  "睡着": "หลับ, นอนหลับ",
  "顺序": "ลำดับ, ระบบ",
  "说不定": "อาจ, อาจจะ",
  "说服": "โน้มน้าว, ชักจูง",
  "思考": "คิด, คิดพิจารณา",
  "似乎": "เหมือน, ดูเหมือน",
  "松": "กรอบ, นุ่ม",
  "松树": "ต้นสน",
  "塑料": "พลาสติก",
  "塑料袋": "ถุงพลาสติก",
  "酸": "เศร้า, รู้สึกเจ็บ",
  "酸奶": "โยเกิร์ต",
  "随手": "สะดวก, ง่าย",
  "孙女": "หลานสาว",
  "孙子": "หลานชาย",
  "缩短": "ย่อสั้น, ลดทอน",
  "缩小": "เล็กลง, หดตัว",
  "台阶": "บันได",
  "台上": "เวที, บนเวที",
  "躺": "นอนราบ, นอน",
  "套餐": "ชุดอาหาร, อาหารชุด",
  "特价": "ราคาพิเศษ",
  "特殊": "พิเศษ",
  "特征": "ลักษณะเฉพาะ, คุณสมบัติ",
  "提供": "จัดหา, ให้",
  "提醒": "เตือน, แจ้งเตือน",
  "体操": "ยืดเส้น, ยืดเหยียด",
  "体检": "การตรวจสุขภาพ",
  "体重": "น้ำหนักตัว",
  "替": "แทน, ให้",
  "替代": "แทนที่, แทน",
  "天真": "ซื่อ, ไร้เดียงสา",
  "填": "เติม, จด",
  "填空": "เติมช่องว่าง",
  "挑": "เลือก, คัด",
  "挑选": "เลือก, คัดเลือก",
  "调皮": "ขี้เล่น, ขี้แย",
  "挑战": "การท้าทาย",
  "贴": "ติด, แปะ",
  "停下": "หยุด, ยุติ",
  "挺": "มาก, ดีมาก",
  "通知书": "ประกาศ, หนังสือแจ้ง",
  "同情": "เห็นใจ, รู้สึกเห็นใจ",
  "童话": "นิทาน, เรื่องเล่า",
  "童年": "วัยเด็ก",
  "统计": "สถิติ",
  "统一": "รวม, ทำให้เป็นหนึ่งเดียว",
  "痛快": "สนุก, พอใจ",
  "投": "ทิ้ง, โยน",
  "投入": "ทิ้งลง, ใส่ลง",
  "投诉": "การร้องเรียน, ข้อร้องเรียน",
  "投资": "การลงทุน, ทุน",
  "透": "ทะลุ, ผ่าน",
  "透明": "โปร่งใส, ใส",
  "图案": "รูปภาพ, ลวดลาย",
  "途中": "ระหว่างทาง, ระหว่าง",
  "土地": "ดิน, แผ่นดิน",
  "推迟": "เลื่อน, ยืด",
  "推销": "ขาย, โปรโมต",
  "脱": "หลุด, หลุดออก",
  "袜子": "ถุงเท้า",
  "外汇": "สกุลเงินต่างประเทศ, สกุลเงิน",
  "外交官": "ทูต, นักการทูต",
  "外套": "เสื้อชั้นนอก, เสื้อผ้าชั้นนอก",
  "弯": "งอ, โค้ง",
  "晚点": "สายด่วน, สาย",
  "万一": "ในกรณีที่, ถ้า",
  "王": "ราชา, พระราชา",
  "网络": "อินเทอร์เน็ต, ระบบเครือข่าย",
  "网址": "ที่อยู่เว็บไซต์, ลิงก์",
  "微笑": "รอยยิ้ม, ยิ้ม",
  "微信": "วีแชท, แอปพลิเคชัน",
  "围巾": "ผ้าพันคอ, ผ้าคลุมคอ",
  "维持": "รักษา, รักษาไว้",
  "维护": "ปกป้อง, รักษา",
  "维修": "ซ่อมแซม, ซ่อม",
  "尾巴": "หาง",
  "未必": "อาจไม่, ไม่จำเป็น",
  "未来": "อนาคต",
  "位于": "อยู่ที่, ตั้งอยู่",
  "位置": "ตำแหน่ง, สถานที่",
  "味儿": "รสชาติ, กลิ่น",
  "喂": "สวัสดี, ฮัลโล",
  "稳": "มั่นคง, คงที่",
  "稳定": "คงที่, คงทน",
  "问候": "ทักทาย, แสดงความเคารพ",
  "无": "ไม่มี, ไม่ได้มี",
  "无法": "ไม่สามารถ, ไม่ได้",
  "无聊": "เบื่อ, น่าเบื่อ",
  "无论": "ไม่ว่า, ไม่ว่าจะ",
  "无数": "จำนวนไม่สิ้นสุด, ไม่มีที่สิ้นสุด",
  "无所谓": "ไม่สำคัญ, ไม่เกี่ยวข้อง",
  "无限": "ไม่มีที่สิ้นสุด, ไม่มีขีดจำกัด",
  "五颜六色": "หลากหลายสี, สีสันสดใส",
  "误会": "ความเข้าใจผิด",
  "西瓜": "แตงกวา",
  "吸": "หยด",
  "吸管": "หลอดดูด",
  "吸收": "ดูดซับ, ดูดซึม",
  "吸烟": "สูบบุหรี่, สูบ",
  "吸引": "ดึงดูด",
  "喜爱": "ชอบ, รัก",
  "系列": "ชุด, ลำดับ",
  "系统": "ระบบ",
  "细": "ละเอียด",
  "细节": "รายละเอียด",
  "细致": "ละเอียด",
  "下个月": "เดือนหน้า",
  "下降": "ลดลง, ลงมา",
  "下楼": "ลงบันได, ลงไปที่ชั้นล่าง",
  "下载": "ดาวน์โหลด",
  "夏季": "ฤดูร้อน",
  "鲜": "ปลา, สด",
  "鲜花": "ดอกไม้",
  "鲜明": "ชัดเจน, สดใส",
  "咸": "นามสกุลเซียน",
  "显著": "เด่นชัด",
  "县": "เขต, อำเภอ",
  "限制": "ข้อจำกัด",
  "相处": "อยู่ร่วมกัน, ปรับตัว",
  "相反": "ตรงข้าม, ขัดแย้ง",
  "箱": "กล่อง",
  "箱子": "กระเป๋าเดินทาง",
  "想念": "คิดถึง",
  "想象": "จินตนาการ",
  "项": "รายการ, หัวข้อ",
  "项目": "กิจกรรม, โครงการ",
  "相片": "รูปถ่าย",
  "消化": "ย่อย, ย่อยอาหาร",
  "销售": "ขาย",
  "小吃": "ของว่าง",
  "小伙子": "ชายหนุ่ม",
  "小型": "ขนาดเล็ก",
  "效率": "ประสิทธิภาพ",
  "些": "บาง",
  "心理": "จิตใจ, จิตวิทยา",
  "新郎": "เจ้าบ่าว",
  "新娘": "เจ้าสาว",
  "新鲜": "สด, ใหม่",
  "新型": "รูปแบบ, รูป",
  "兴奋": "ตื่นเต้น, กระตือรือร้น",
  "形容": "อธิบาย, บรรยาย",
  "形势": "สถานการณ์, ภาวะ",
  "型": "รูป, รูปทรง",
  "型号": "รุ่น, แบบ",
  "醒": "ตื่น, ฟื้น",
  "兴趣": "ความสนใจ, ความชอบ",
  "性质": "ลักษณะ, คุณสมบัติ",
  "兄弟": "พี่น้อง, พี่น้องชาย",
  "胸部": "หน้าอก, อก",
  "修理": "ซ่อม, ซ่อมแซม",
  "选择": "เลือก, คัด",
  "学分": "หน่วย, คะแนน",
  "学年": "ปีการศึกษา, ปี",
  "学时": "ชั่วโมงเรียน, ชั่วโมง",
  "学术": "วิชาการ, วิชา",
  "学问": "ความรู้, วิชา",
  "寻找": "หา, ค้นหา",
  "迅速": "เร็ว, รวดเร็ว",
  "牙": "ฟัน",
  "牙刷": "แปรงฟัน, แปรง",
  "亚运会": "กีฬาเอเชีย, เอเชียนเกมส์",
  "呀": "(คำช่วย)",
  "延长": "ยืด, ยืดออก",
  "延期": "เลื่อน, ล่าช้า",
  "延续": "ต่อเนื่อง, ต่อไป",
  "严": "นามสกุลหยัน, นามสกุล",
  "严格": "เข้มงวด, รัดกุม",
  "严重": "ความรุนแรง, รุนแรง",
  "研究": "ศึกษา, วิจัย",
  "研究生": "นักศึกษาวิจัย, นักศึกษาปริญญาโท",
  "研制": "ผลิต, สร้าง",
  "盐": "เกลือ, น้ำเกลือ",
  "眼镜": "แว่นตา, แว่นตาใส",
  "眼泪": "น้ำตา, น้ำตาไหล",
  "眼里": "ในตา, ในสายตา",
  "演讲": "การบรรยาย, การพูดในที่สาธารณะ",
  "阳台": "ระเบียง, ลานบ้าน",
  "养成": "ปลูกฝัง, สร้างนิสัย",
  "腰": "เอว, ท้อง",
  "摇": "แกว่ง, โยก",
  "药物": "ยา, ยาที่ใช้รักษา",
  "要": "ต้องการ, อยาก",
  "业余": "งานอดิเรก, งานนอกเวลา",
  "叶子": "ใบไม้, ใบไม้ของพืช",
  "医疗": "การรักษา, การบำบัด",
  "医学": "วิชาการแพทย์, วิชาการรักษา",
  "依靠": "พึ่งพา, อาศัย",
  "依然": "ยังคง, ยัง",
  "一律": "เท่ากัน, ทั่วไป",
  "一再": "ซ้ำแล้วซ้ำอีก, ซ้ำ",
  "一致": "ตรงกัน, ตรงกันข้าม",
  "移": "ย้าย, ย้ายไป",
  "移动": "เคลื่อนที่, ย้าย",
  "移民": "ผู้อพยพ, ผู้ย้ายถิ่น",
  "遗产": "มรดก, ของขวัญ",
  "遗传": "ถ่ายทอด, สืบทอด",
  "疑问": "คำถาม, ข้อสงสัย",
  "以及": "และ",
  "以内": "ภายใน",
  "一般来说": "โดยทั่วไป",
  "义务": "หน้าที่",
  "议论": "การอภิปราย",
  "引": "อ้างอิง",
  "引导": "นำทาง",
  "引进": "แนะนำ",
  "引起": "กระตุ้น",
  "应": "ควร",
  "英勇": "กล้าหาญ",
  "营业": "ดำเนินธุรกิจ",
  "赢得": "คว้ามาได้",
  "影子": "เงา",
  "勇敢": "กล้า",
  "勇气": "ความกล้า",
  "用途": "วัตถุประสงค์",
  "优良": "ดีเยี่ยม",
  "优美": "สง่างาม",
  "优秀": "ยอดเยี่ยม",
  "邮局": "ไปรษณีย์",
  "有劲儿": "มีพลัง",
  "有趣": "สนุก",
  "有限": "จำกัด",
  "幼儿园": "โรงเรียนอนุบาล",
  "于是": "ดังนั้น",
  "语法": "ไวยากรณ์",
  "语音": "การออกเสียง",
  "玉": "หยก",
  "玉米": "ข้าวโพด",
  "预测": "คาดการณ์, คำนวณ",
  "预订": "สั่งจอง, จัดการ",
  "遇": "พบ, พบกัน",
  "遇到": "พบเจอ, พบกัน",
  "遇见": "พบ, พบกัน",
  "原料": "วัตถุดิบ, วัตถุ",
  "原则": "หลักการ, กฎ",
  "圆": "กลม, วงกลม",
  "圆满": "สมบูรณ์, สำเร็จ",
  "约会": "นัด, หมายถึงการนัด",
  "月底": "สิ้นเดือน, ปลายเดือน",
  "阅读": "อ่าน, ศึกษา",
  "运动会": "การแข่งขันกีฬา, การแข่งขัน",
  "运动员": "นักกีฬา",
  "运气": "โชค, ดวง",
  "运用": "ใช้, นำใช้",
  "再三": "ซ้ำแล้วซ้ำอีก, หลายครั้ง",
  "在乎": "ใส่ใจ, สนใจ",
  "在于": "อยู่ที่, อยู่ใน",
  "赞成": "สนับสนุน, ให้ความเห็นชอบ",
  "赞赏": "ชื่นชม",
  "赞助": "สนับสนุน, ให้การสนับสนุน",
  "造型": "รูปแบบ, การออกแบบ",
  "战斗": "ต่อสู้",
  "战胜": "เอาชนะ, ชนะ",
  "战士": "ทหาร, ผู้ต่อสู้",
  "战争": "สงคราม, ความขัดแย้ง",
  "丈夫": "สามี, ผู้ชาย",
  "招呼": "ทักทาย, ดูแล",
  "着": "(แสดงสถานะ)",
  "着火": "จุดไฟ",
  "着急": "กังวล",
  "召开": "ประชุม",
  "折": "หน่วย",
  "针": "เข็ม",
  "针对": "ตาม",
  "阵": "เหตุการณ์",
  "争论": "โต้เถียง",
  "征服": "พิชิต",
  "征求": "ขอความเห็น",
  "政府": "รัฐบาล",
  "政治": "การเมือง",
  "之后": "หลังจากนั้น",
  "之间": "ระหว่าง",
  "之前": "ก่อนหน้านี้",
  "之一": "หนึ่งใน",
  "支": "หน่วย",
  "植物": "พืช",
  "指挥": "ควบคุม",
  "制订": "วางแผน",
  "质量": "น้ำหนัก",
  "治": "ศึกษา",
  "治疗": "การรักษา",
  "智力": "ความฉลาด",
  "智能": "ความฉลาด",
  "中介": "เป็นผู้ประสานงาน",
  "种类": "ชนิด",
  "中奖": "ถูกรางวัล",
  "种": "หน่วย",
  "种植": "ปลูก",
  "重量": "น้ำหนัก",
  "逐步": "ค่อยเป็นค่อยไป, ทีละขั้น",
  "逐渐": "ค่อยๆ, ค่อยเป็นค่อยไป",
  "主题": "หัวข้อ, เรื่อง",
  "主席": "ประธาน",
  "祝福": "อวยพร, ขอให้",
  "著名": "มีชื่อเสียง, โด่งดัง",
  "著作": "ผลงาน, งานเขียน",
  "抓紧": "จับให้แน่น, จับ",
  "专心": "จดจ่อกับ",
  "转动": "หมุน",
  "转告": "ส่งต่อ, บอก",
  "转身": "หันหลัง, หันกลับ",
  "转弯": "เลี้ยว, หมุน",
  "转移": "ย้าย, ถ่ายโอน",
  "装修": "ซ่อมแซม, ปรับปรุง",
  "装置": "ติดตั้ง, ตั้ง",
  "追求": "แสวงหา, ตามหา",
  "准时": "ตรงเวลา, ทันเวลา",
  "资料": "ข้อมูล, วัสดุ",
  "资源": "ทรัพยากร, แหล่ง",
  "自": "จาก, ด้วย",
  "自信": "ความมั่นใจในตัวเอง, ความมั่นใจ",
  "字母": "ตัวอักษร",
  "综合": "รวม, รวมทั้งหมด",
  "总共": "รวมทั้งหมด, รวม",
  "总理": "นายกรัฐมนตรี",
  "总统": "ประธานาธิบดี",
  "总之": "ในที่สุด, สรุปแล้ว",
  "阻止": "ขัดขวาง, หยุด",
  "嘴巴": "ปาก, ริมฝีปาก",
  "最初": "เริ่มต้น, ครั้งแรก",
  "作出": "สร้าง, ตัดสินใจ",
  "作为": "ถือว่า, มองว่า",
  "做梦": "ฝัน"
}
