{
  "安慰": "สนับสนุน, ปลอบใจ",
  "岸": "ฝั่ง",
  "岸上": "บนบก",
  "按摩": "นวด",
  "拔": "เปลือย",
  "白酒": "เหล้าขาวที่กลั่นจากข้าวโพดหรือข้าวฟ่าง",
  "拜访": "เยี่ยมเยียน",
  "版": "แผ่น",
  "扮演": "แสดงบทบาท",
  "棒": "ดี",
  "包围": "ล้อมรอบ",
  "包装": "บรรจุภัณฑ์",
  "保卫": "ปกป้อง",
  "保养": "ดูแลสุขภาพ",
  "报答": "ตอบแทน",
  "报警": "แจ้งเตือน",
  "抱怨": "บ่น",
  "背包": "กระเป๋าเป้",
  "悲剧": "ละคร tragic",
  "悲伤": "เศร้า",
  "北极": "ขั้วโลกเหนือ",
  "被动": "แบบ被动",
  "辈": "ช่วงชีวิต",
  "本人": "ตัวฉันเอง",
  "鼻子": "จมูก",
  "比方": "ตัวอย่าง",
  "比重": "สัดส่วน",
  "彼此": "ซึ่งกันและกัน",
  "必": "แน่นอน",
  "必需": "จำเป็น",
  "毕竟": "ในที่สุด, อย่างแน่นอน",
  "闭幕": "ปิดฉาก, ปิด幕",
  "闭幕式": "พิธีปิด, งานปิด",
  "边境": "ชายแดน, เส้นขอบ",
  "编辑": "แก้ไข, ปรับปรุง",
  "变动": "การเปลี่ยนแปลง, การเปลี่ยน",
  "便利": "อำนวยความสะดวก, ทำให้เป็นประโยชน์",
  "便条": "โน้ต, บันทึก",
  "便于": "สะดวก, ง่าย",
  "宾馆": "โรงแรม, บ้านพัก",
  "饼": "เค้กกลม, ขนมปังกลม",
  "饼干": "อัลมอนด์, ขนมปังกรอบ",
  "病毒": "ไวรัส, ไวรัสคอมพิวเตอร์",
  "玻璃": "พลาสติก, แก้ว",
  "博客": "บล็อก",
  "博览会": "นิทรรศการ, งานแสดง",
  "博士": "ปริญญาเอก, นักวิชาการ",
  "博物馆": "พิพิธภัณฑ์, หอจดหมายเหตุ",
  "薄弱": "อ่อนแอ, ไม่แข็งแรง",
  "不顾": "ไม่สนใจ",
  "不利": "ไม่ดี, ไม่เป็นประโยชน์",
  "不耐烦": "ไม่อดทน, หงุดหงิด",
  "不幸": "ไม่ดี",
  "不易": "ไม่สบาย",
  "补偿": "ชดเชย, ชดใช้",
  "补贴": "เงินชดเชย, ค่าชดเชย",
  "不曾": "ยังไม่เคย",
  "不得了": "ร้ายแรง, แย่มาก",
  "不敢当": "ไม่กล้ารับ",
  "不良": "ไม่ดี",
  "不免": "ไม่สามารถหลีกเลี่ยงได้",
  "不能不": "ต้อง",
  "不时": "บ่อยครั้ง",
  "不停": "ไม่หยุด",
  "不许": "ห้าม",
  "不止": "ต่อเนื่อง",
  "不足": "ไม่เพียงพอ",
  "部位": "ส่วน",
  "猜": "เดา",
  "猜测": "คาดเดา",
  "裁判": "ผู้ตัดสิน",
  "采购": "เลือกและซื้อ",
  "彩票": "ตั๋วหวย",
  "餐馆": "ร้านอาหาร",
  "餐厅": "ห้องอาหาร",
  "餐饮": "อาหารและเครื่องดื่ม",
  "草原": "ทุ่งหญ้า",
  "册": "เล่ม",
  "层次": "ระดับ",
  "叉": "ส้อม",
  "叉子": "ส้อม",
  "差别": "ความแตกต่าง",
  "差距": "ช่องว่าง",
  "插": "ใส่",
  "查询": "สอบถาม",
  "差点儿": "ใกล้จะ",
  "拆": "แบ่งออก",
  "拆除": "รื้อถอน",
  "产业": "ทรัพย์สิน",
  "长度": "ความยาว",
  "长寿": "ความยาวนานของชีวิต, ชื่อเขต",
  "肠": "ลำไส้",
  "尝": "ลองชิม, ลิ้มรส",
  "尝试": "ลองทำ, ทดลอง",
  "厂长": "ผู้จัดการโรงงาน",
  "场面": "เหตุการณ์, สถานการณ์",
  "倡导": "สนับสนุน, เสนอ",
  "超越": "ข้าม, ล้ำ",
  "车主": "เจ้าของยานพาหนะ",
  "称": "เรียก, ชื่อ",
  "称号": "ชื่อ, ตำแหน่ง",
  "成本": "ต้นทุน",
  "成交": "ทำธุรกรรม, ทำสัญญา",
  "成效": "ผลลัพธ์, ผล",
  "成语": "สำนวนจีน",
  "承办": "รับผิดชอบ, รับมอบ",
  "城里": "ในเมือง",
  "乘": "ขึ้น, นั่ง",
  "乘车": "ขึ้นรถ, นั่งรถ",
  "乘客": "ผู้โดยสาร",
  "乘坐": "นั่งรถ, ขึ้นรถ",
  "吃力": "ใช้แรงมาก, ลำบาก",
  "池子": "บ่อน้ำ, บ่อ",
  "迟": "สายล่าช้า, ช้า",
  "冲动": "อารมณ์, ความตื่นเต้น",
  "冲突": "ความขัดแย้ง",
  "充足": "เพียงพอ, มากพอ",
  "愁": "กังวล, ห่วงใย",
  "丑": "นามสกุลโจว",
  "臭": "กลิ่น",
  "出版": "การพิมพ์",
  "出差": "เดินทางเพื่อทำงาน",
  "出汗": "เหงื่อ",
  "出于": "จาก",
  "初期": "ระยะเริ่มต้น",
  "除非": "ถ้าไม่",
  "除夕": "วันสุดท้ายของปีเก่า",
  "厨房": "ห้องครัว",
  "处罚": "ลงโทษ",
  "处分": "การลงโทษ",
  "处在": "อยู่ใน",
  "传达": "ส่งต่อ",
  "传递": "ส่งผ่าน",
  "传真": "ภาพถ่าย",
  "窗帘": "ผ้าม่านหน้าต่าง",
  "闯": "พุ่งเข้าไป",
  "创立": "ก่อตั้ง",
  "辞典": "พจนานุกรม",
  "辞职": "ลาออก",
  "此后": "ต่อมา",
  "此刻": "ขณะนี้",
  "此时": "ในขณะนี้",
  "聪明": "ฉลาด",
  "从而": "ดังนั้น",
  "从中": "จากนั้น",
  "脆": "เปราะ",
  "存款": "เงินฝาก",
  "寸": "นิ้ว",
  "达成": "บรรลุ",
  "答": "คำตอบ",
  "答复": "คำตอบ",
  "打": "กระทำ",
  "打扮": "แต่งตัว",
  "打包": "ห่อ",
  "打击": "ช็อค",
  "打架": "ต่อสู้",
  "打扰": "รบกวน",
  "大胆": "กล้าหาญ",
  "大都": "ส่วนใหญ่",
  "大纲": "โครงสร้าง",
  "大伙儿": "ทุกคน",
  "大奖赛": "การแข่งขันใหญ่",
  "大脑": "สมอง",
  "大事": "เรื่องสำคัญ",
  "大厅": "ห้องโถงใหญ่",
  "大象": "ช้าง",
  "大熊猫": "หมีแพนด้า",
  "大于": "มากกว่า",
  "大致": "ประมาณ",
  "呆": "โง่",
  "待": "รอ",
  "代价": "ค่าตอบแทน",
  "代理": "ตัวแทน",
  "带有": "มี",
  "贷款": "สินเชื่อ",
  "单一": "เดียว",
  "胆": "ตับ",
  "胆小": "กลัว",
  "蛋糕": "เค้ก",
  "当场": "ทันที",
  "当代": "ยุคปัจจุบัน, ยุคสมัย",
  "当年": "ในอดีต, เมื่อครั้งนั้น",
  "当前": "ปัจจุบัน, ขณะนี้",
  "当选": "get elected",
  "挡": "ward off",
  "到来": "arrive",
  "倒是": "actually",
  "道德": "value orientation",
  "得了": "all right!",
  "得以": "can",
  "等候": "hold back",
  "等级": "graduated table",
  "低于": "be lower than",
  "地带": "belt",
  "地形": "topography",
  "地震": "quake",
  "递": "to hand over",
  "递给": "Handle",
  "典礼": "religious rite",
  "点燃": "light_up",
  "电池": "galvanic pile",
  "电饭锅": "electric rice cooker",
  "电子版": "e-edition",
  "调动": "to transfer",
  "丢": "discard",
  "动机": "motif",
  "动手": "attack",
  "动态": "situation",
  "动员": "mobilize",
  "冻": "to freeze",
  "洞": "รู, ช่อง",
  "豆制品": "ผลิตภัณฑ์จากถั่ว, ถั่วแปรรูป",
  "毒": "พิษ, สารพิษ",
  "堆": "กอง, ปึก",
  "对立": "ต่อต้าน, ขัดแย้ง",
  "对应": "ความสัมพันธ์, การสอดคล้อง",
  "吨": "ตัน, หน่วยน้ำหนัก",
  "朵": "ดอก, ชิ้น",
  "躲": "หลบ, หลบหนี",
  "儿女": "ลูกชายและลูกสาว, ลูก",
  "耳朵": "หู, ชิ้นส่วนรับเสียง",
  "二维码": "บาร์โค้ดสองมิติ, รหัสสองมิติ",
  "发布": "เผยแพร่, ออก",
  "发觉": "ค้นพบ, รู้สึก",
  "发射": "ปล่อย, ยิง",
  "发行": "ออก, แจกจ่าย",
  "罚": "ลงโทษ",
  "罚款": "ปรับ, ปรับเงิน",
  "法规": "กฎหมาย, ระบบกฎหมาย",
  "法制": "ระบบกฎหมาย, ระบบทางกฎหมาย",
  "繁荣": "เจริญรุ่งเรือง, บุกเบิก",
  "返回": "กลับ, ย้อนกลับ",
  "防治": "ป้องกันและรักษา",
  "放大": "ขยาย, ขยายใหญ่",
  "放弃": "ละทิ้ง, ทิ้ง",
  "分成": "แบ่ง, แบ่งออก",
  "分解": "แบ่ง, แบ่งออก",
  "分类": "จัดประเภท, จัดกลุ่ม",
  "分离": "แยก, แยกออก",
  "分析": "วิเคราะห์",
  "分享": "แบ่งปัน, แบ่งส่วน",
  "丰收": "ผลผลิตอุดมสมบูรณ์, ผลผลิตมาก",
  "风度": "ความสง่างาม, น้ำใจ",
  "风光": "ทัศนียภาพ, บรรยากาศ",
  "封": "หน่วย, ทหาร",
  "疯": "บ้า, คลั่ง",
  "疯狂": "บ้า, คลั่ง",
  "扶": "สนับสนุน, ช่วยเหลือ",
  "服从": "เชื่อฟัง, ปฏิบัติตาม",
  "幅": "มุม, ทิศทาง",
  "幅度": "ความกว้าง, ความกว้างของคลื่น",
  "福利": "ความสุข, ความเป็นอยู่ที่ดี",
  "辅助": "ช่วย, สนับสนุน",
  "负责人": "ผู้รับผิดชอบ, ผู้จัดการ",
  "附件": "ไฟล์แนบ, 附件",
  "改革": "การปฏิรูป, การเปลี่ยนแปลง",
  "干脆": "ตรงไปตรงมา, ตรง",
  "干扰": "รบกวน",
  "干预": "แทรกแซง, แทรก",
  "感想": "ความรู้สึก, ความคิด",
  "钢笔": "ปากกาหมึก, ปากกา",
  "钢琴": "เปียโน, กลอง",
  "高大": "สูงและใหญ่, ใหญ่",
  "高度": "สูง, ความสูง",
  "高跟鞋": "รองเท้าส้นสูง",
  "高温": "อุณหภูมิสูง, ความร้อน",
  "高于": "มากกว่า, สูงกว่า",
  "高原": "ที่ราบสูง, ภูเขา",
  "搞": "ทำงาน, จัดการ",
  "搞好": "ทำให้ดี, จัดการให้ดี",
  "歌曲": "เพลง, จังหวะ",
  "隔壁": "ข้างเคียง, บ้านข้างๆ",
  "个儿": "ขนาด, ความใหญ่",
  "跟前": "ด้านหน้า, ตรงหน้า",
  "跟随": "ตาม, ตามหลัง",
  "更换": "เปลี่ยน, แทนที่",
  "更新": "อัปเดต, ปรับปรุง",
  "工艺": "เทคโนโลยี, วิธีการ",
  "工作日": "วันทำงาน, วันทำการ",
  "公告": "ประกาศ, แจ้ง",
  "公认": "ยอมรับ, รับรอง",
  "公式": "สูตร, สมการ",
  "公正": "ยุติธรรม, ไม่ลำเอียง",
  "共计": "รวมทั้งหมด, รวมไปถึง",
  "共享": "แบ่งปัน, ใช้ร่วมกัน",
  "沟": "คู, ราง",
  "沟通": "สื่อสาร, ติดต่อ",
  "估计": "ประมาณ, คาดการณ์",
  "古老": "โบราณ, ดั้งเดิม",
  "鼓": "กลอง",
  "鼓励": "ส่งเสริม, กระตุ้น",
  "鼓掌": "ปรบมือ, ชื่นชม",
  "顾问": "ที่ปรึกษา, ผู้ให้คำแนะนำ",
  "怪": "แปลก, ประหลาด",
  "关怀": "ห่วงใย, ดูแล",
  "关键": "จุดสำคัญ, หัวใจ",
  "冠军": "แชมป์, ผู้ชนะ",
  "光荣": "เกียรติ, ความภาคภูมิ",
  "光线": "รังสี, แสง",
  "广": "กว้าง, แพร่หลาย",
  "广泛": "กว้างขวาง, แพร่หลาย",
  "规划": "วางแผน, จัดการ",
  "鬼": "แผนร้าย, ความชั่วร้าย",
  "柜子": "ตู้, ตู้เก็บของ",
  "滚": "เดือด, ต้ม",
  "锅": "หม้อ, กระทะ",
  "国籍": "สัญชาติ, ชาติกำเนิด",
  "国民": "พลเมือง, ประชาชน",
  "过度": "มากเกินไป, มากเกิน",
  "过敏": "แพ้ภูมิ, แพ้สาร",
  "过于": "มากเกินไป, มากเกิน",
  "害": "ทำอันตราย, ทำร้าย",
  "汗": "ผู้นำ, ผู้ปกครอง",
  "好运": "โชคดี, โชค",
  "号召": "เรียกร้อง, ขอ",
  "合并": "รวม, ผสาน",
  "合成": "ประกอบ, สร้าง",
  "盒": "กล่องเล็ก, กล่อง",
  "盒饭": "อาหารในกล่อง, อาหารกล่อง",
  "盒子": "กล่อง, กล่องใส่ของ",
  "贺卡": "บัตรอวยพร, บัตรข้อความ",
  "恨": "เสียใจ, ผิดหวัง",
  "猴": "ลิง, สัตว์ลิง",
  "后悔": "เสียใจ, ผิดหวัง",
  "胡同儿": "ทางเดิน, ถนนเล็ก",
  "胡子": "เครา, หนวด",
  "虎": "เสือ, สัตว์เสือ",
  "华语": "ภาษาจีน, ภาษาจีนกลาง",
  "滑": "ลื่น, ลื่นเท้า",
  "化石": "หินปูน, หิน",
  "划分": "แบ่ง, แบ่งออก",
  "画面": "กรอบ, ภาพ",
  "环节": "ส่วน, ช่วง",
  "慌": "ตื่นตระหนก, ตกใจ",
  "慌忙": "รีบเร่ง, ตื่นตระหนก",
  "灰色": "สีเทา, ท้อแท้",
  "恢复": "ฟื้นฟู, ฟื้น",
  "回报": "คืน, ตอบ",
  "回避": "หลีกเลี่ยง, หลีก",
  "回顾": "ทบทวน, มองย้อนกลับ",
  "回收": "รีไซเคิล, คืน",
  "回头": "หันกลับ, หันหลัง",
  "回信": "ตอบกลับ, ตอบ",
  "回忆": "นึกถึง, ระลึก",
  "汇款": "โอนเงิน, ส่งเงิน",
  "会谈": "สนทนา, ประชุม",
  "活力": "พลัง, ความกระปรี้กระเปร่า",
  "活泼": "กระปรี้กระเปร่า, สนุกสนาน",
  "火柴": "ไม้ขีด, ไม้จุดไฟ",
  "火腿": "ขาหมู, หมูปิ้ง",
  "火灾": "อัคคีภัย, ไฟไหม้",
  "或是": "หรือ, หรือว่า",
  "机器人": "หุ่นยนต์, หุ่น",
  "机制": "กลไก, ระบบ",
  "肌肉": "กล้ามเนื้อ, กล้าม",
  "基地": "ฐาน, ฐานทัพ",
  "基金": "เงินทุน, ทุน",
  "即使": "แม้ว่า, ถึงแม้",
  "集团": "กลุ่ม, องค์กร",
  "挤": "บีบ, บีบอัด",
  "记忆": "ความจำ, ความทรงจำ",
  "技能": "ทักษะ, ความสามารถ",
  "继承": "สืบทอด, สืบสาน",
  "加热": "ให้ความร้อน, ทำให้ร้อน",
  "加上": "เพิ่มเติม, รวมทั้ง",
  "加速": "เร่ง, ทำให้เร็วขึ้น",
  "加以": "จัดการ, ปฏิบัติ",
  "夹": "บีบ, บีบอัด",
  "甲": "ตัวที่หนึ่ง, แรก",
  "价": "ราคา, ค่า",
  "驾驶": "ขับ, ขับรถ",
  "驾照": "ใบขับขี่, ใบอนุญาตขับรถ",
  "坚定": "มั่นคง, แน่วแน่",
  "肩": "ไหล่, บ่า",
  "艰苦": "ยากลำบาก, ขมักเขม้น",
  "艰难": "ยากเย็น, ท้าทาย",
  "检验": "ทดสอบ, ตรวจสอบ",
  "减轻": "ลดลง, ผ่อนคลาย",
  "剪": "นามสกุลเจียน, นามสกุลจิ้น",
  "剪刀": "กรรไกร, เครื่องตัด",
  "剪子": "กรรไกร, เครื่องตัด",
  "间接": "ทางอ้อม, ผ่านทาง",
  "建造": "สร้าง, สร้างขึ้น",
  "建筑": "ก่อสร้าง, สร้าง",
  "健全": "สมบูรณ์, สมบูรณ์แบบ",
  "键": "คีย์, ปุ่ม",
  "键盘": "คีย์บอร์ด, แป้นพิมพ์",
  "将": "จะ, กำลัง",
  "将要": "จะ, กำลัง",
  "奖励": "รางวัล, ของรางวัล",
  "交代": "มอบหมาย, ถ่ายโอน",
  "郊区": "ชานเมือง, พื้นที่ชานเมือง",
  "胶带": "เทปใส, เทปติด",
  "胶水": "กาว, สารกาว",
  "脚步": "เสียงเท้า, รอยเท้า",
  "接触": "สัมผัส, พบกัน",
  "接连": "ต่อเนื่อง, ไม่หยุด",
  "解除": "ถอดออก, ปลด",
  "解放": "ปลดปล่อย, ปลด",
  "戒": "หลีกเลี่ยง, ห้าม",
  "届": "เหตุการณ์, งาน",
  "今日": "วันนี้, วันนี้เอง",
  "尽管": "แม้ว่า, ถึงแม้",
  "紧紧": "แน่น, แน่นหนา",
  "尽可能": "อย่างเต็มที่, ทั้งหมดที่สามารถ",
  "进化": "วิวัฒนาการ, การพัฒนา",
  "近来": "ล่าสุด, ไม่นานมานี้",
  "经费": "ค่าใช้จ่าย, เงินทุน",
  "景象": "ภาพ, ทัศนียภาพ",
  "警告": "เตือน, แจ้งเตือน",
  "竞赛": "การแข่งขัน, การแข่ง",
  "竞争": "การแข่งขัน, การแข่ง",
  "酒鬼": "คนเมา, คนดื่ม",
  "救灾": "ช่วยเหลือผู้ประสบภัย, ช่วยเหลือ",
  "居然": "ไม่น่าเชื่อ, แปลกใจ",
  "局面": "สถานการณ์, ภาพรวม",
  "局长": "หัวหน้าแผนก, ผู้จัดการ",
  "举动": "การกระทำ, ท่าที",
  "拒绝": "ปฏิเสธ",
  "俱乐部": "คลับ, ชมรม",
  "剧本": "บทบาท",
  "决不": "ไม่เคย",
  "绝望": "หมดหวัง",
  "军人": "ทหาร",
  "开幕": "เปิด",
  "开幕式": "พิธีเปิด",
  "看成": "มองว่า",
  "看出": "รับรู้",
  "看待": "มองว่า",
  "考核": "สอบ",
  "烤肉": "บาร์บีคิว",
  "烤鸭": "เป็ดปิ้ง",
  "靠近": "เข้าใกล้",
  "颗": "เม็ด",
  "咳": "เสียงถอนหายใจ",
  "可": "สามารถ",
  "可怜": "เห็นใจ",
  "可惜": "เสียดาย",
  "渴望": "ปรารถนา",
  "刻": "หน่วย",
  "客户": "ลูกค้า",
  "客气": "สุภาพ",
  "客厅": "ห้องนั่งเล่น",
  "课题": "หัวข้อ",
  "肯定": "ยืนยัน",
  "空中": "ในอากาศ",
  "控制": "ควบคุม",
  "口号": "สโลแกน",
  "库": "คลัง",
  "快活": "สนุก",
  "宽度": "ความกว้าง",
  "狂": "บ้า",
  "亏": "ขาด",
  "困扰": "ความสับสน, ความวิตกกังวล",
  "落": "ตก, หล่น",
  "来信": "จดหมายที่ส่งมา, จดหมายที่เข้ามา",
  "烂": "เน่า, บูด",
  "朗读": "อ่านเสียงดัง, อ่านออกเสียง",
  "浪漫": "ไม่จริงจัง, ผิดปกติ",
  "劳动": "งาน, แรงงาน",
  "梨": "ลูกพีช, ลูกแพร",
  "礼": "ของขวัญ",
  "礼拜": "สัปดาห์, วันอาทิตย์",
  "礼貌": "มารยาท, ความนอบน้อม",
  "厉害": "แย่มาก, รุนแรง",
  "立": "ตั้ง, ตั้งขึ้น",
  "立场": "มุมมอง, ทัศนคติ",
  "利润": "กำไร, ผลกำไร",
  "例外": "ข้อยกเว้น",
  "连接": "เชื่อม, เชื่อมโยง",
  "联络": "ติดต่อ",
  "联想": "การเชื่อมโยง, การคิดเชื่อมโยง",
  "脸盆": "ถังล้างหน้า, ถัง",
  "脸色": "สีหน้า, ใบหน้า",
  "恋爱": "ความรัก",
  "两岸": "สองฝั่ง",
  "邻居": "เพื่อนบ้าน",
  "铃": "ระฆัง, ระฆังเล็ก",
  "铃声": "เสียงระฆัง, เสียง",
  "领带": "เสื้อผ้าคอเสื้อ, ผ้าคล้องคอ",
  "令": "คำสั่ง, บัญชา",
  "流动": "ไหล, ไหลเวียน",
  "流通": "หมุนเวียน, กระจาย",
  "漏": "รั่ว, รั่วซึม",
  "漏洞": "ช่องโหว่, ช่องว่าง",
  "逻辑": "ตรรกะ, ความคิด",
  "落实": "กำหนด, ตัดสินใจล่วงหน้า",
  "码头": "ศูนย์การค้า, ศูนย์ขนส่ง",
  "骂": "ตำหนิ, ด่า",
  "买卖": "การซื้อขาย, การค้า",
  "漫长": "ยาวนาน, นานมาก",
  "漫画": "การ์ตูน, ภาพการ์ตูน",
  "毛笔": "ปากกาจีน, ปากกาเขียน",
  "矛盾": "ขัดแย้ง, ขัดกัน",
  "冒": "เสี่ยง, รับความเสี่ยง",
  "贸易": "การค้า, การซื้อขาย",
  "煤": "ถ่านหิน, ใช้เป็นเชื้อเพลิง",
  "煤气": "ก๊าซถ่านหิน, แก๊ส",
  "门诊": "บริการผู้ป่วยนอก, คลินิก",
  "迷人": "ดึงดูด, หลงใหล",
  "迷信": "เชื่ออย่างไม่เห็นเหตุผล, ศรัทธา",
  "面貌": "ลักษณะ, รูปแบบ",
  "面子": "ชื่อเสียง, ความนิยม",
  "秒": "นาที, เครื่องวัดเวลา",
  "敏感": "ไว, ละเอียด",
  "明亮": "สว่าง, แจ่มใส",
  "明明": "ชัดเจน, แน่นอน",
  "命令": "คำสั่ง, บัญชา",
  "模范": "ต้นแบบ, ตัวอย่าง",
  "模仿": "เลียนแบบ, ทำตาม",
  "模糊": "ความมัวหมอง, คลุมเครือ",
  "模式": "ตัวอย่าง, รูปแบบ",
  "摩擦": "แรงเสียดทาน, ความขัดแย้ง",
  "摩托": "มอเตอร์, รถมอเตอร์ไซค์",
  "模样": "ลักษณะ, รูปร่าง",
  "目光": "สายตา, ความสนใจ",
  "耐心": "ความอดทน, ความใจเย็น",
  "男性": "พี่ชาย, ผู้ชาย",
  "南北": "ทิศเหนือและใต้, ทิศทาง",
  "南极": "ขั้วโลกใต้, จุดสุดท้าย",
  "难得": "หายาก, ไม่ค่อยพบ",
  "难以": "ยากที่จะ",
  "脑子": "สมอง, หัว",
  "内在": "ภายใน, ความเป็นจริง",
  "能量": "พลังงาน, กำลัง",
  "年度": "ปี, ปีการศึกษา",
  "年龄": "อายุ, วัย",
  "年前": "ก่อนปี, หลายปีก่อน",
  "牛": "วัว, สัตว์",
  "牛仔裤": "กางเกงยีนส์, กางเกง",
  "农产品": "ผลผลิตทางการเกษตร, ผลิตภัณฑ์เกษตร",
  "女性": "ผู้หญิง, หญิง",
  "暖": "อุ่น, ความอบอุ่น",
  "偶尔": "บางครั้ง, ครั้งคราว",
  "偶然": "บังเอิญ, ความบังเอิญ",
  "偶像": "ตุ๊กตา",
  "拍摄": "ถ่ายทำ, ถ่ายภาพ",
  "排除": "กำจัด, ขับไล่",
  "旁": "ด้านข้าง, ข้าง",
  "陪": "เพื่อน, ผู้ร่วม",
  "赔": "ชดใช้, ชดเชย",
  "赔偿": "ชดใช้, ชดเชย",
  "配备": "อุปกรณ์, ของใช้",
  "配套": "จัดเป็นชุด, จัดให้ครบชุด",
  "喷": "พุ่ง, กระฉอก",
  "盆": "อ่าง, ถัง",
  "披": "คลุม, ห่อ",
  "皮肤": "หนัง, ผิวหนัง",
  "皮鞋": "รองเท้าหนัง, รองเท้าผิวหนัง",
  "脾气": "ตับ, ตับอ่อน",
  "匹": "หน่วย, หน่วยการวัด",
  "骗": "หลอกลวง, หลอก",
  "骗子": "คนหลอกลวง, ผู้หลอกลวง",
  "拼": "ประกอบ, ต่อกัน",
  "频道": "ช่อง, ช่องทาง",
  "频繁": "บ่อย, ถี่",
  "品": "สินค้า, ของ",
  "品种": "สายพันธุ์, ชนิด",
  "平坦": "ราบ, ราบเรียบ",
  "平原": "ที่ราบ, ที่ราบลุ่ม",
  "评估": "ประมาณ, ประเมิน",
  "评论": "ความคิดเห็น, ความคิด",
  "凭": "ตาม, อาศัย",
  "泼": "สาด, กระเด็น",
  "葡萄": "องุ่น, ผลองุ่น",
  "葡萄酒": "ไวน์องุ่น, ไวน์",
  "期望": "ความคาดหวัง, ความหวัง",
  "齐全": "ครบ, สมบูรณ์",
  "其": "ของ, ของที่",
  "启动": "เปิดใช้งาน, เริ่มต้น",
  "启发": "เปิดเผยความคิด, กระตุ้น",
  "启事": "ประกาศ, ข่าวประชาสัมพันธ์",
  "起到": "เล่น, ทำหน้าที่",
  "起码": "อย่างน้อย, ขั้นต่ำ",
  "气体": "ไอเสีย, ของเสีย",
  "气象": "สภาพอากาศ, ภูมิอากาศ",
  "签": "เซ็นชื่อ, ลงชื่อ",
  "签订": "ทำสัญญา, ลงนามในสัญญา",
  "签名": "ลายเซ็น, ชื่อผู้ลงนาม",
  "签约": "ลงนามในสัญญา, ทำสัญญา",
  "签证": "วีซ่า",
  "签字": "ลายเซ็น, ชื่อผู้ลงนาม",
  "前景": "ทิศทาง, อนาคต",
  "前提": "เงื่อนไข, ข้อกำหนด",
  "欠": "ขาด, ไม่เพียงพอ",
  "枪": "ปืน, อาวุธ",
  "强度": "ความแข็งแรง, ความเข้มข้น",
  "墙壁": "ผนัง, เนินดิน",
  "抢": "ปล้น, ขโมย",
  "抢救": "ช่วยชีวิต, รีบช่วย",
  "强迫": "บังคับ, บีบบังคับ",
  "悄悄": "เงียบๆ, ลับๆ",
  "敲": "ตี, กระแทก",
  "敲门": "เคาะประตู",
  "瞧": "ดู, มอง",
  "琴": "เครื่องดนตรี, หุ่นเชิด",
  "勤奋": "ขยัน, ขยันขันแข็ง",
  "青": "สีเขียว, สีธรรมชาติ",
  "清晨": "เช้าตรู่, ช่วงเช้า",
  "清理": "ทำความสะอาด, จัดการ",
  "情节": "เรื่องราว, โครงเรื่อง",
  "情形": "สภาพ, สถานการณ์",
  "晴朗": "แจ่มใส, ไม่มีเมฆ",
  "区域": "พื้นที่, พื้นที่เขต",
  "全都": "ทั้งหมด",
  "全世界": "ทั่วโลก, ทั่วทั้งโลก",
  "泉": "น้ำพุ, น้ำไหล",
  "劝": "ชักจูง, กระตุ้น",
  "缺乏": "ขาดแคลน, ไม่มี",
  "确立": "ตั้งราก, สร้าง",
  "群体": "ประชากร, กลุ่ม",
  "群众": "ฝูง, กลุ่ม",
  "染": "ย้อม, สี",
  "绕": "ล้อมรอบ, วนรอบ",
  "热量": "ความร้อน",
  "热门": "นิยม, ได้รับความนิยม",
  "人间": "โลกมนุษย์, โลก",
  "人力": "พลังงาน, กำลัง",
  "人士": "บุคคลที่มีชื่อเสียง, บุคคล",
  "人物": "ตัวละคร, บุคคล",
  "忍": "อดทน",
  "忍不住": "ไม่สามารถอดทนได้, ไม่สามารถควบคุมได้",
  "忍受": "อดทน, ทน",
  "认": "รู้จัก, รู้",
  "认定": "เชื่อแน่, ยืนยัน",
  "扔": "ทิ้ง, โยน",
  "仍旧": "ยัง, ยังคง",
  "如此": "ดังนั้น, ดังนี้",
  "如同": "เหมือน, คล้าย",
  "如下": "ดังนี้, ดังที่กล่าวไว้",
  "入门": "ประตูเข้า, ทางเข้า",
  "软": "นุ่ม, นิ่ม",
  "软件": "ซอฟต์แวร์, โปรแกรม",
  "洒": "พ่น, ราด",
  "散": "แยก, กระจาย",
  "散文": "บทกวีแบบไม่ใช้จังหวะ, ข้อความทั่วไป",
  "杀": "ลดลง, ลด",
  "杀毒": "โปรแกรมป้องกันไวรัส, ตัวป้องกันไวรัส",
  "沙漠": "ทะเลทราย, ที่แห้งแล้ง",
  "傻": "โง่, ไม่ฉลาด",
  "山区": "พื้นที่ภูเขา, พื้นที่ที่มีภูเขา",
  "扇": "พัด, ใบพัด",
  "扇子": "พัด, ใบพัด",
  "商标": "เครื่องหมายการค้า, แบรนด์",
  "上级": "ผู้บังคับบัญชา, ระดับสูง",
  "上下": "บน-ล่าง, ข้างบน-ข้างล่าง",
  "上涨": "เพิ่มขึ้น, ขึ้น",
  "稍": "เล็กน้อย, น้อย",
  "稍微": "ค่อนข้าง, พอประมาณ",
  "蛇": "งู, สัตว์เลื้อยคลาน",
  "舍不得": "ไม่อยากทำ, ไม่ยอม",
  "舍得": "กล้าที่จะทำ, ยอมเสีย",
  "设想": "จินตนาการ, คิดถึง",
  "社": "สังคม, กลุ่ม",
  "社区": "ชุมชน, พื้นที่",
  "射": "ยิง, ปล่อย",
  "射击": "ยิง, ยิงปืน",
  "摄像": "ถ่ายวิดีโอ, ถ่ายภาพเคลื่อนไหว",
  "摄像机": "กล้องวิดีโอ, กล้องถ่ายวิดีโอ",
  "摄影": "ถ่ายภาพ, ภาพถ่าย",
  "摄影师": "นักถ่ายภาพ",
  "伸": "ยืด",
  "深处": "ลึก",
  "深度": "การวัดความลึก",
  "神": "เทพ",
  "神经": "ระบบประสาท",
  "神奇": "เวทมนตร์",
  "神情": "สีหน้า",
  "升高": "ขึ้น",
  "生成": "สร้าง",
  "声": "เสียง",
  "胜负": "ชัยชนะหรือความพ่ายแพ้",
  "剩": "เหลือ",
  "剩下": "เหลืออยู่",
  "失误": "ข้อผิดพลาด",
  "师傅": "จักรพรรดิ",
  "诗歌": "บทกวี",
  "十足": "100 เปอร์เซ็นต์",
  "时常": "บ่อยครั้ง",
  "时光": "เวลา",
  "时机": "จังหวะ",
  "时事": "เหตุการณ์",
  "实惠": "ประโยชน์ที่ชัดเจน",
  "拾": "ขึ้นบันไดอย่างระมัดระวัง",
  "使得": "ทำให้",
  "示范": "สาธิต",
  "式": "ประเภท",
  "势力": "อำนาจ",
  "试图": "พยายาม",
  "视频": "วิดีโอ",
  "视为": "ถือว่า",
  "收购": "ซื้อมา",
  "收集": "รวบรวม",
  "收拾": "จัดการ",
  "手段": "ทรัพยากร",
  "手法": "วิธีการ",
  "寿司": "ซูชิ",
  "受灾": "ประสบภัย",
  "瘦": "ผอม",
  "书法": "การเขียนตัวอักษร",
  "书柜": "ตู้หนังสือ",
  "书桌": "โต๊ะเขียนหนังสือ",
  "输出": "ส่งออก",
  "蔬菜": "ผัก",
  "熟悉": "คุ้นเคย",
  "鼠": "หนู",
  "鼠标": "เมาส์ (คอมพิวเตอร์)",
  "数目": "จำนวน",
  "摔": "ทิ้ง",
  "摔倒": "ล้ม",
  "率领": "นำหน้า",
  "双手": "มือเปล่า",
  "水产品": "ผลิตภัณฑ์จากน้ำ",
  "水分": "ความชื้น",
  "水库": "เขื่อน",
  "水灾": "น้ำท่วม",
  "睡眠": "การนอนหลับ",
  "说法": "วิธีพูด",
  "硕士": "ปริญญาโท",
  "私人": "ส่วนตัว",
  "思维": "ความคิด, ความคิดเห็น",
  "四周": "รอบด้าน, ทั่วทั้ง",
  "搜": "ค้นหา, ค้น",
  "搜索": "ค้นหา, ค้นหาที่",
  "宿舍": "ห้องพัก, ที่พัก",
  "酸甜苦辣": "รสชาติ, ความรู้สึก",
  "随后": "ต่อมา, หลังจากนั้น",
  "随意": "ตามใจ, ตามที่ต้องการ",
  "随着": "ตาม, พร้อมกับ",
  "岁月": "เวลา, ช่วงเวลา",
  "碎": "แตก, หัก",
  "损害": "ความเสียหาย, ความเสีย",
  "损失": "การสูญเสีย, ความสูญเสีย",
  "所在": "ที่ตั้ง, สถานที่",
  "锁": "ล็อก, ปิดล็อก",
  "台风": "พายุ, พายุหมุน",
  "抬": "ยก, ยกขึ้น",
  "抬头": "เงยหน้าขึ้น, มองขึ้น",
  "太空": "ท้องฟ้า, จักรวาล",
  "弹": "ดึง, ดีด",
  "逃": "หลบหนี, หนี",
  "逃跑": "หนี, หลบหนี",
  "逃走": "หนี, หลบหนี",
  "桃": "พีช, ลูกพีช",
  "桃花": "ดอกพีช, ดอกไม้พีช",
  "桃树": "ต้นพีช, ต้นไม้พีช",
  "讨厌": "ไม่ชอบ",
  "特定": "เฉพาะ, เฉพาะเจาะจง",
  "特性": "คุณสมบัติ, ลักษณะ",
  "特有": "เฉพาะ, ที่มีอยู่",
  "提倡": "สนับสนุน",
  "提起": "กล่าวถึง",
  "提示": "ชี้ให้เห็น",
  "题材": "subject_matter",
  "体积": "volume",
  "体力": "breath",
  "天才": "genius",
  "天然气": "natural gas",
  "天文": "astronomy",
  "调节": "regulate",
  "调解": "to mediate",
  "厅": "department",
  "停留": "stay for a time or at a place",
  "通用": "common (use)",
  "偷": "steal",
  "偷偷": "on the QT",
  "突破": "make a breakthrough",
  "土豆": "potato",
  "吐": "articulation",
  "兔": "rabbit",
  "团长": "head of delegation",
  "推行": "carry out",
  "脱离": "depart",
  "外界": "external world",
  "完了": "to be finished",
  "微博": "micro-blogging",
  "为难": "disoblige",
  "为期": "by/lasting (a definite time)",
  "为止": "until",
  "为主": "give first place to",
  "违法": "ผิดกฎหมาย, ละเมิด",
  "违反": "ฝ่าฝืน, ละเมิด",
  "违规": "ฝ่าฝืนกฎ, ละเมิดกฎ",
  "围绕": "ล้อมรอบ, เกี่ยวข้องกับ",
  "唯一": "เพียงหนึ่งเดียว, ไม่มีใครเหมือน",
  "委托": "มอบหมาย, มอบหมายให้",
  "卫星": "ดาวเทียม",
  "胃": "กระเพาะอาหาร",
  "慰问": "แสดงความเห็นใจ, ปลอบใจ",
  "温和": "อ่อนโยน, นุ่มนวล",
  "文艺": "วรรณกรรมและศิลปะ",
  "卧室": "ห้องนอน",
  "握": "จับ, ถือ",
  "污染": "ปนเปื้อน, ทำให้สกปรก",
  "污水": "น้ำทิ้ง, น้ำเสีย",
  "屋": "บ้าน, หลังคา",
  "无奈": "ไร้ทางเลือก, ไม่มีทาง",
  "无疑": "แน่นอน, ไม่ต้องสงสัย",
  "舞": "เต้น, รำ",
  "物价": "ราคาสินค้า",
  "物业": "อสังหาริมทรัพย์",
  "物质": "สิ่งของ",
  "误解": "เข้าใจผิด, คลาดเคลื่อน",
  "西红柿": "มะเขือเทศ",
  "西装": "ชุดสูท",
  "喜剧": "ละครเวที, ละคร",
  "戏": "ละคร",
  "戏剧": "ตกใจ, ทำให้ตกใจ",
  "吓": "ก่อนหลัง, ลำดับ",
  "先后": "early or late",
  "先前": "ก่อนหน้านี้",
  "鲜艳": "สีสันสดใส",
  "闲": "ว่าง",
  "显": "แสดง",
  "现有": "มีอยู่แล้ว",
  "现状": "สถานการณ์",
  "线索": "เบาะแส",
  "献": "ถวาย",
  "乡": "บ้านเกิด",
  "乡村": "ชนบท",
  "相等": "เท่ากัน",
  "相应": "สอดคล้อง",
  "香肠": "ไส้กรอก",
  "详细": "ละเอียด",
  "享受": "เพลิดเพลิน",
  "向导": "ผู้นำทาง",
  "向前": "ไปข้างหน้า",
  "向上": "ขึ้นไป",
  "相声": "บทสนทนาตลก",
  "象征": "สัญลักษณ์",
  "消除": "ขจัด",
  "消毒": "ฆ่าเชื้อ",
  "消防": "ป้องกันไฟ",
  "消费者": "ผู้บริโภค",
  "消极": "เชิงลบ",
  "小偷儿": "ขโมย",
  "歇": "พัก",
  "协议": "ข้อตกลง",
  "协议书": "สัญญา",
  "斜": "เอียง",
  "心态": "ทัศนคติ, ความรู้สึกเห็นใจ",
  "心疼": "รู้สึกเจ็บปวด, รัก",
  "辛苦": "พยายาม, ทุ่มเท",
  "欣赏": "ชื่นชม, รับรู้คุณค่า",
  "信念": "ความเชื่อ, ความมั่นคง",
  "信箱": "กล่องจดหมาย, ตู้จดหมาย",
  "行驶": "เคลื่อนที่, วิ่ง",
  "形态": "ลักษณะ, รูปแบบ",
  "性能": "ประสิทธิภาพ, ความสามารถ",
  "雄伟": "ยิ่งใหญ่, สง่างาม",
  "熊": "หมี",
  "休闲": "ว่าง, วันหยุด",
  "修复": "ซ่อมแซม, ฟื้นฟู",
  "修建": "สร้าง, สร้างขึ้น",
  "修养": "การฝึกฝน, ความรู้",
  "虚心": "อ่อนน้อม, ถ่อมตัว",
  "许可": "อนุญาต, ให้สิทธิ์",
  "选修": "เลือกเรียน, เรียนเพิ่มเติม",
  "学科": "สาขา, วิชา",
  "学位": "ปริญญา, วุฒิการศึกษา",
  "学者": "นักวิชาการ, ผู้เชี่ยวชาญ",
  "寻求": "ค้นหา, หา",
  "询问": "สอบถาม, ถาม",
  "押金": "เงินมัดจำ, ค่ามัดจำ",
  "鸭子": "ไก่งวง, นกเป็ด",
  "亚军": "อันดับสอง, รองชนะเลิศ",
  "延伸": "ขยาย, ยืด",
  "严厉": "เข้มงวด, จริงจัง",
  "严肃": "จริงจัง",
  "言语": "ภาษาพูด, คำพูด",
  "研究所": "สถาบัน, มหาวิทยาลัย",
  "眼光": "สายตา, ความคิด",
  "邀请": "เชิญ, ขอ",
  "摇头": "ส่ายหัว, ปฏิเสธ",
  "咬": "กัด, กลืน",
  "也好": "คำช่วย: แสดงความไม่แน่ใจ, (ใน ~也好)",
  "业务": "บริการ, งาน",
  "夜间": "เวลากลางคืน, ยามค่ำ",
  "一流": "คุณภาพสูงสุด, ระดับสูง",
  "依法": "ตามกฎหมาย, ตามหลักกฎหมาย",
  "依旧": "เหมือนเดิม, ยังคง",
  "依据": "ตาม, ตามที่",
  "依照": "ตาม, ตามที่",
  "一辈子": "ตลอดชีวิต, ตลอดไป",
  "一带": "พื้นที่, ย่าน",
  "一旦": "เมื่อ, ถ้า",
  "一句话": "ในทันที, ทันที",
  "一路": "ในที่สุด, ด้วยคำพูด",
  "一下儿": "ลอง, ทำสักครั้ง",
  "一下子": "ในเวลาสั้น, ไม่นาน",
  "一向": "อย่างปกติ, ทุกครั้ง",
  "乙": "ตัวอักษรที่สอง",
  "以便": "เพื่อให้, เพื่อ",
  "以往": "ในอดีต, ที่ผ่านมา",
  "一口气": "ไม่หยุด",
  "一身": "ทั้งตัว, ทั้งร่างกาย",
  "意识": "ความตระหนัก, ความรู้สึก",
  "意味着": "หมายถึง, แสดงถึง",
  "意志": "จิตใจ, จิต",
  "因而": "ดังนั้น",
  "饮料": "เครื่องดื่ม, อาหาร",
  "饮食": "โภชนาการ, อาหาร",
  "印刷": "พิมพ์, พิมพ์ออก",
  "应": "ควร, ควรจะ",
  "硬": "แข็ง, แข็งกระด้าง",
  "硬件": "ฮาร์ดแวร์, อุปกรณ์",
  "拥抱": "กอด, โอบกอด",
  "拥有": "มี, ครอบครอง",
  "用不着": "ไม่จำเป็น, ไม่ต้อง",
  "用户": "ลูกค้า, ผู้ใช้",
  "用来": "เพื่อ, เพื่อให้",
  "用于": "ใช้ใน, ใช้สำหรับ",
  "优惠": "ส่วนลด, ความพิเศษ",
  "优先": "สิทธิพิเศษ, ความสำคัญก่อน",
  "幽默": "อารมณ์ขัน, ความตลก",
  "尤其": "โดยเฉพาะ, อย่างมาก",
  "由此": "ดังนั้น, ด้วยเหตุนี้",
  "犹豫": "ลังเล, ไม่แน่ใจ",
  "游泳池": "สระน้ำ, สนามเด็กเล่น",
  "友谊": "ความสัมพันธ์, ความเป็นมิตร",
  "有毒": "พิษ, สารพิษ",
  "有害": "อันตราย, ทำลาย",
  "有力": "แข็งแกร่ง, ทรงพลัง",
  "有利于": "เป็นประโยชน์ต่อ, ดีต่อ",
  "有着": "มี, มีอยู่",
  "羽毛球": "ลูกขนไก่, ลูกเตะ",
  "羽绒服": "เสื้อผ้าที่ใส่ขนเป็ด, เสื้อผ้าที่มีขน",
  "雨水": "น้ำฝน, น้ำตก",
  "预备": "เตรียม, จัดเตรียม",
  "预期": "คาดการณ์, คาดไว้",
  "元旦": "วันขึ้นปีใหม่",
  "园林": "สวน",
  "原理": "หลักการ",
  "原始": "ต้นฉบับ",
  "原先": "เดิม",
  "原有": "เดิมที",
  "远处": "ไกล",
  "怨": "ตำหนิ",
  "愿": "ความปรารถนา",
  "约束": "การควบคุม",
  "月饼": "ขนมไหว้พระจันทร์",
  "月球": "ดวงจันทร์",
  "阅览室": "ห้องอ่านหนังสือ",
  "运": "การขนส่ง",
  "运行": "เคลื่อนที่",
  "灾": "ภัยพิบัติ",
  "灾害": "ภัย",
  "灾难": "ภัยพิบัติ",
  "灾区": "พื้นที่ภัยพิบัติ",
  "再次": "อีกครั้ง",
  "再也": "(ไม่) อีกแล้ว",
  "在场": "อยู่ที่นั่น",
  "在内": "รวมถึง",
  "暂时": "ชั่วคราว",
  "暂停": "หยุดชั่วคราว",
  "糟": "เหตุการณ์ร้าย",
  "糟糕": "แย่มาก",
  "早期": "ยุคเริ่มต้น",
  "增": "เพิ่ม",
  "增产": "เพิ่มผลผลิต",
  "增大": "ขยาย, เพิ่มขึ้น",
  "增多": "เพิ่มขึ้น, มากขึ้น",
  "增强": "เสริม, แข็งแรงขึ้น",
  "赠": "ให้เป็นของขวัญ, มอบ",
  "赠送": "ของขวัญ, ให้เป็นของขวัญ",
  "摘": "เก็บ, ตัด",
  "展览": "แสดง, จัดแสดง",
  "展示": "เปิดเผย, แสดง",
  "展现": "ปรากฏ, แสดงออก",
  "占领": "ยึดครอง, ยึด",
  "占有": "มี, ถือครอง",
  "涨": "เพิ่มขึ้น, ขึ้น",
  "涨价": "ราคาสูงขึ้น, ราคาเพิ่ม",
  "掌握": "ควบคุม, จับ",
  "招生": "รับสมัคร, รับนักเรียน",
  "招手": "โบกมือ, ยกมือ",
  "珍贵": "มีค่า, ราคาสูง",
  "珍惜": "รักษา, คุ้มครอง",
  "珍珠": "ไข่มุก, ลูกมุก",
  "真诚": "ซื่อสัตย์, จริงใจ",
  "真理": "ความจริง, ความเป็นจริง",
  "真相": "ความจริง, ข้อเท็จจริง",
  "诊断": "วินิจฉัย, วินิจฉัยโรค",
  "振动": "สั่น, เขย่า",
  "震惊": "ตกใจ, ประหลาดใจ",
  "争议": "ขัดแย้ง, โต้เถียง",
  "正版": "ของแท้, ของแท้จริง",
  "正规": "เป็นทางการ, ตามหลัก",
  "正如": "เหมือน, ตามที่",
  "正义": "ความยุติธรรม, ความถูกต้อง",
  "证实": "ยืนยัน, ยืนยันว่า",
  "证书": "ใบรับรอง, หลักฐาน",
  "挣": "ต่อสู้, ดิ้นรน",
  "挣钱": "หาเงิน, ทำงานเพื่อหาเงิน",
  "之内": "ภายใน, ภายในของ",
  "之外": "ภายนอก, นอกเหนือจาก",
  "之下": "ภายใต้, ภายใต้เงื่อนไข",
  "之中": "ภายใน, ระหว่าง",
  "支出": "ค่าใช้จ่าย",
  "支配": "จัดการ, ควบคุม",
  "执行": "ดำเนินการ, ปฏิบัติ",
  "直线": "เส้นตรง",
  "值班": "ทำงานกะ, ทำงานช่วงเวลา",
  "职能": "หน้าที่",
  "职位": "ตำแหน่ง",
  "职务": "หน้าที่",
  "只不过": "เพียงแต่, เพียง",
  "只见": "เพียงแต่เห็น, เห็นเพียง",
  "指标": "ตัวชี้วัด, ตัวชี้",
  "指甲": "เล็บ, เล็บมือ",
  "指示": "ชี้ให้เห็น, ชี้แนะ",
  "指责": "ตำหนิ",
  "至": "ถึง, ไปถึง",
  "制成": "ตัดแต่ง, ตัด",
  "制约": "จำกัด, ควบคุม",
  "治安": "ความสงบ, ความปลอดภัย",
  "治理": "บริหาร, จัดการ",
  "中断": "ตัดขาด, หยุดชะงัก",
  "中秋节": "เทศกาลไหว้พระจันทร์, วันไหว้พระจันทร์",
  "中央": "ศูนย์กลาง",
  "中药": "ยาจีน",
  "终点": "จุดสิ้นสุด",
  "终身": "ตลอดชีวิต",
  "终止": "หยุด",
  "中毒": "พิษ",
  "众多": "จำนวนมาก",
  "周期": "ช่วงเวลา",
  "竹子": "ต้นไม้สีเขียว",
  "主办": "ผู้จัดงาน",
  "主导": "ผู้นำ",
  "主观": "มุมมองส่วนตัว",
  "主管": "ผู้ดูแล",
  "主体": "ส่วนหลัก",
  "助理": "ผู้ช่วย",
  "助手": "ผู้ช่วยงาน",
  "注册": "ลงทะเบียน",
  "注射": "ฉีด",
  "注视": "จ้องมอง",
  "注重": "ให้ความสำคัญ",
  "祝贺": "แสดงความยินดี",
  "专辑": "ชุดเพลง",
  "专利": "สิทธิบัตร",
  "转化": "เปลี่ยนแปลง",
  "转换": "เปลี่ยน",
  "转让": "โอน",
  "转向": "เปลี่ยนทิศทาง",
  "装饰": "การตกแต่ง",
  "撞": "กระแทก",
  "资本": "ทุน",
  "资产": "สินทรัพย์",
  "资助": "สนับสนุน",
  "子弹": "กระสุน",
  "仔细": "ระมัดระวัง",
  "紫": "สีม่วง",
  "自豪": "ภูมิใจ",
  "自杀": "ฆ่าตัวตาย",
  "自愿": "อาสา",
  "总裁": "ผู้จัดการ",
  "总数": "จำนวนรวม",
  "总算": "ในที่สุด",
  "总体": "โดยรวม",
  "阻碍": "ขัดขวาง",
  "组织": "เนื้อเยื่อ",
  "醉": "เมา",
  "尊敬": "เคารพ",
  "尊重": "เคารพ",
  "遵守": "ปฏิบัติตาม"
}
